{"method": "cobyla", "cost_hamiltonian": {"n_qubits": 8, "terms": [{"qubit_indices": [0, 1], "pauli_str": "ZZ", "phase": 1}, {"qubit_indices": [0, 2], "pauli_str": "ZZ", "phase": 1}, {"qubit_indices": [1, 2], "pauli_str": "ZZ", "phase": 1}, {"qubit_indices": [3, 4], "pauli_str": "ZZ", "phase": 1}, {"qubit_indices": [3, 5], "pauli_str": "ZZ", "phase": 1}, {"qubit_indices": [3, 6], "pauli_str": "ZZ", "phase": 1}, {"qubit_indices": [3, 7], "pauli_str": "ZZ", "phase": 1}, {"qubit_indices": [4, 5], "pauli_str": "ZZ", "phase": 1}, {"qubit_indices": [4, 6], "pauli_str": "ZZ", "phase": 1}, {"qubit_indices": [4, 7], "pauli_str": "ZZ", "phase": 1}, {"qubit_indices": [5, 6], "pauli_str": "ZZ", "phase": 1}, {"qubit_indices": [5, 7], "pauli_str": "ZZ", "phase": 1}, {"qubit_indices": [6, 7], "pauli_str": "ZZ", "phase": 1}, {"qubit_indices": [0, 3], "pauli_str": "ZZ", "phase": 1}, {"qubit_indices": [0, 4], "pauli_str": "ZZ", "phase": 1}, {"qubit_indices": [0, 5], "pauli_str": "ZZ", "phase": 1}, {"qubit_indices": [0, 6], "pauli_str": "ZZ", "phase": 1}, {"qubit_indices": [0, 7], "pauli_str": "ZZ", "phase": 1}, {"qubit_indices": [1, 3], "pauli_str": "ZZ", "phase": 1}, {"qubit_indices": [1, 4], "pauli_str": "ZZ", "phase": 1}, {"qubit_indices": [1, 5], "pauli_str": "ZZ", "phase": 1}, {"qubit_indices": [1, 6], "pauli_str": "ZZ", "phase": 1}, {"qubit_indices": [1, 7], "pauli_str": "ZZ", "phase": 1}, {"qubit_indices": [2, 3], "pauli_str": "ZZ", "phase": 1}, {"qubit_indices": [2, 4], "pauli_str": "ZZ", "phase": 1}, {"qubit_indices": [2, 5], "pauli_str": "ZZ", "phase": 1}, {"qubit_indices": [2, 6], "pauli_str": "ZZ", "phase": 1}, {"qubit_indices": [2, 7], "pauli_str": "ZZ", "phase": 1}, {"qubit_indices": [0], "pauli_str": "Z", "phase": 1}, {"qubit_indices": [1], "pauli_str": "Z", "phase": 1}, {"qubit_indices": [2], "pauli_str": "Z", "phase": 1}, {"qubit_indices": [3], "pauli_str": "Z", "phase": 1}, {"qubit_indices": [4], "pauli_str": "Z", "phase": 1}, {"qubit_indices": [5], "pauli_str": "Z", "phase": 1}, {"qubit_indices": [6], "pauli_str": "Z", "phase": 1}, {"qubit_indices": [7], "pauli_str": "Z", "phase": 1}], "coeffs": [4.0, 8.0, 16.0, 16.0, 4.0, 12.0, 8.0, 8.0, 24.0, 16.0, 6.0, 4.0, 12.0, 4.0, 8.0, 2.0, 6.0, 4.0, 8.0, 16.0, 4.0, 12.0, 8.0, 16.0, 32.0, 8.0, 24.0, 16.0, -18.0, -36.0, -72.0, -35.0, -71.0, -17.5, -53.0, -35.0], "constant": 131.5, "qubits_pairs": [{"qubit_indices": [0, 1], "pauli_str": "ZZ", "phase": 1}, {"qubit_indices": [0, 2], "pauli_str": "ZZ", "phase": 1}, {"qubit_indices": [1, 2], "pauli_str": "ZZ", "phase": 1}, {"qubit_indices": [3, 4], "pauli_str": "ZZ", "phase": 1}, {"qubit_indices": [3, 5], "pauli_str": "ZZ", "phase": 1}, {"qubit_indices": [3, 6], "pauli_str": "ZZ", "phase": 1}, {"qubit_indices": [3, 7], "pauli_str": "ZZ", "phase": 1}, {"qubit_indices": [4, 5], "pauli_str": "ZZ", "phase": 1}, {"qubit_indices": [4, 6], "pauli_str": "ZZ", "phase": 1}, {"qubit_indices": [4, 7], "pauli_str": "ZZ", "phase": 1}, {"qubit_indices": [5, 6], "pauli_str": "ZZ", "phase": 1}, {"qubit_indices": [5, 7], "pauli_str": "ZZ", "phase": 1}, {"qubit_indices": [6, 7], "pauli_str": "ZZ", "phase": 1}, {"qubit_indices": [0, 3], "pauli_str": "ZZ", "phase": 1}, {"qubit_indices": [0, 4], "pauli_str": "ZZ", "phase": 1}, {"qubit_indices": [0, 5], "pauli_str": "ZZ", "phase": 1}, {"qubit_indices": [0, 6], "pauli_str": "ZZ", "phase": 1}, {"qubit_indices": [0, 7], "pauli_str": "ZZ", "phase": 1}, {"qubit_indices": [1, 3], "pauli_str": "ZZ", "phase": 1}, {"qubit_indices": [1, 4], "pauli_str": "ZZ", "phase": 1}, {"qubit_indices": [1, 5], "pauli_str": "ZZ", "phase": 1}, {"qubit_indices": [1, 6], "pauli_str": "ZZ", "phase": 1}, {"qubit_indices": [1, 7], "pauli_str": "ZZ", "phase": 1}, {"qubit_indices": [2, 3], "pauli_str": "ZZ", "phase": 1}, {"qubit_indices": [2, 4], "pauli_str": "ZZ", "phase": 1}, {"qubit_indices": [2, 5], "pauli_str": "ZZ", "phase": 1}, {"qubit_indices": [2, 6], "pauli_str": "ZZ", "phase": 1}, {"qubit_indices": [2, 7], "pauli_str": "ZZ", "phase": 1}], "qubits_singles": [{"qubit_indices": [0], "pauli_str": "Z", "phase": 1}, {"qubit_indices": [1], "pauli_str": "Z", "phase": 1}, {"qubit_indices": [2], "pauli_str": "Z", "phase": 1}, {"qubit_indices": [3], "pauli_str": "Z", "phase": 1}, {"qubit_indices": [4], "pauli_str": "Z", "phase": 1}, {"qubit_indices": [5], "pauli_str": "Z", "phase": 1}, {"qubit_indices": [6], "pauli_str": "Z", "phase": 1}, {"qubit_indices": [7], "pauli_str": "Z", "phase": 1}], "single_qubit_coeffs": [-18.0, -36.0, -72.0, -35.0, -71.0, -17.5, -53.0, -35.0], "pair_qubit_coeffs": [4.0, 8.0, 16.0, 16.0, 4.0, 12.0, 8.0, 8.0, 24.0, 16.0, 6.0, 4.0, 12.0, 4.0, 8.0, 2.0, 6.0, 4.0, 8.0, 16.0, 4.0, 12.0, 8.0, 16.0, 32.0, 8.0, 24.0, 16.0]}, "evals": {"number_of_evals": 21, "jac_evals": 0, "qfim_evals": 0}, "most_probable_states": {"solutions_bitstrings": ["00011111"], "bitstring_energy": 187.0}, "intermediate": {"angles": [[0.980247473377, 0.601747103253, 0.431160589402], [1.980247473377, 0.601747103253, 0.431160589402], [0.980247473377, 1.601747103253, 0.431160589402], [0.980247473377, 0.601747103253, 1.431160589402], [0.730989122497, -0.274306043729, 0.018363837744], [0.855618297937, 0.163720529762, 0.224762213573], [0.918406252745, 0.821261979939, 0.328745344716], [0.858769114479, 1.037981189501, 0.219309537292], [0.862529931644, 1.139977761361, -0.00890649103], [0.620189279482, 1.201293111831, -0.005524759767], [1.062007190079, 1.279562426086, 0.047882105898], [0.915148993638, 1.037780769487, -0.058018700986], [0.913880900491, 1.173032949643, 0.004385706913], [0.861454293256, 1.153053853131, -0.037268813327], [0.840974296034, 1.113688904561, 0.04353872402], [0.851989781861, 1.151587546872, -0.03593759576], [0.879762017518, 1.115055977201, -0.016556483887], [0.879857437738, 1.107320628719, -0.002980921142], [0.88623437635, 1.118876927138, -0.014424801692], [0.874583717855, 1.110986445692, -0.030725631741], [0.873464310948, 1.122192325108, -0.013488678403]], "cost": [123.6376, 128.2622, 139.8914, 131.2964, 152.762, 128.671, 118.7934, 108.1716, 106.3978, 141.0382, 118.2392, 110.8358, 111.9438, 114.2392, 122.4488, 142.489, 99.2572, 108.8132, 103.9514, 126.1908, 100.6584], "measurement_outcomes": [{"11010110": 1, "01111001": 1, "00000101": 3, "00111101": 2, "00001011": 4, "01110000": 2, "11101001": 1, "10011010": 1, "01001111": 1, "00110001": 3, "11010011": 8, "00011110": 2, "01011011": 2, "00110111": 1, "10110101": 7, "11101110": 8, "11110000": 4, "10011100": 2, "11011000": 12, "10111010": 1, "10001010": 3, "01010001": 4, "00010001": 5, "01001000": 11, "01101110": 11, "00101011": 2, "11111000": 4, "01110010": 19, "11000001": 1, "11111110": 8, "01111110": 9, "11000011": 4, "00001110": 3, "11100101": 19, "11111100": 14, "01101101": 11, "00100000": 5, "10100000": 11, "01000010": 19, "10101110": 4, "11010010": 10, "10101101": 13, "00111010": 9, "10010011": 14, "11011111": 25, "10110110": 79, "10000010": 5, "10100101": 40, "11101100": 43, "11001011": 10, "10101111": 14, "00001001": 5, "01010011": 1, "11101111": 9, "01010100": 13, "01011111": 19, "10111100": 6, "11100010": 11, "00001111": 2, "11110001": 38, "00000010": 2, "00111011": 9, "01111100": 22, "10111000": 32, "00111110": 9, "00011100": 11, "11001100": 22, "10111011": 26, "00011000": 10, "10000110": 4, "01110111": 4, "11000010": 20, "11110010": 75, "11010101": 15, "11100000": 61, "10001110": 22, "00000100": 19, "10110100": 39, "01101010": 57, "01111000": 26, "00101111": 19, "00110000": 26, "00001010": 43, "01010000": 7, "11100110": 24, "11001111": 13, "11110100": 12, "00010011": 31, "01001110": 19, "11101010": 15, "01100011": 30, "01101000": 25, "11100011": 71, "00000011": 3, "01110110": 20, "00010101": 24, "11000111": 3, "10010100": 8, "10110011": 104, "00111001": 33, "10000000": 30, "10000100": 39, "01111011": 28, "10000011": 46, "01100101": 12, "01100100": 108, "00001100": 4, "00100100": 9, "01111010": 12, "00010010": 11, "10001000": 2, "00111111": 73, "00010110": 20, "11110101": 39, "10010111": 38, "01000110": 20, "01110001": 2, "01001101": 7, "10110000": 70, "00010111": 25, "10011111": 45, "01010111": 5, "10100001": 68, "01100010": 20, "00110100": 34, "10011000": 11, "11001010": 3, "00100101": 47, "11000100": 65, "00101010": 21, "11001101": 7, "01101100": 16, "10100011": 50, "01000001": 5, "10111110": 8, "11011100": 20, "00010000": 31, "10011011": 77, "11101101": 14, "01100001": 2, "10110111": 51, "10101100": 4, "10000101": 7, "01000111": 6, "01011101": 8, "01110100": 13, "10010110": 12, "10011101": 1, "10010101": 29, "01010110": 2, "00100010": 62, "11111001": 5, "00000001": 38, "00101100": 13, "00011010": 3, "01110101": 28, "11001000": 26, "01100111": 19, "00011001": 12, "00100001": 17, "11111101": 13, "10110001": 64, "11110110": 21, "11101011": 7, "11011110": 15, "11000110": 6, "01000100": 51, "10010001": 48, "01101011": 9, "11011010": 11, "10101000": 14, "01100000": 43, "10100111": 58, "01011000": 23, "10010010": 39, "01001100": 27, "11110011": 31, "10001011": 8, "00000000": 9, "10001001": 11, "01011110": 3, "01010010": 20, "10110010": 53, "00001101": 6, "01000101": 13, "01101001": 35, "10101001": 38, "00111000": 1, "01001001": 17, "01010101": 3, "00101101": 20, "01111101": 11, "00011111": 109, "11100111": 21, "11100100": 76, "10111111": 1, "00001000": 13, "11010100": 27, "10111001": 45, "00100111": 7, "01000011": 43, "10011110": 34, "11011011": 9, "10100110": 12, "10001111": 34, "01011100": 7, "01111111": 34, "01101111": 7, "00000111": 20, "10001100": 4, "00111100": 31, "01001010": 22, "00011011": 31, "11011001": 12, "00011101": 38, "10101010": 12, "01110011": 35, "10111101": 17, "10100100": 54, "00110011": 63, "10011001": 58, "11001110": 12, "11011101": 8, "00101000": 30, "00101110": 5, "10100010": 51, "11001001": 20, "10000111": 19, "11010001": 17, "01000000": 14, "11111011": 6, "11111111": 8, "00110101": 20, "11111010": 7, "00110110": 9, "00100110": 2, "11000101": 33, "11000000": 5, "11101000": 16}, {"10001111": 2, "01100111": 1, "01111100": 3, "00101000": 1, "00001001": 3, "10000001": 2, "00101101": 4, "10010010": 2, "00011000": 2, "11100011": 4, "01011001": 4, "01110010": 4, "00001011": 8, "01000000": 1, "00000100": 7, "00011100": 7, "00101001": 3, "00000001": 3, "10010100": 1, "01111011": 2, "11010011": 7, "00111101": 2, "01010001": 8, "11001010": 1, "10011000": 6, "01001111": 1, "01010101": 11, "00100100": 5, "00001100": 9, "00010010": 11, "10100101": 16, "11011000": 1, "01101011": 1, "00111010": 3, "01001011": 20, "00110000": 20, "11001101": 7, "01010010": 8, "01011110": 2, "00100011": 2, "00110010": 1, "10101011": 7, "01111101": 3, "11101010": 4, "00101010": 2, "01001000": 8, "11011111": 24, "00111100": 6, "11110000": 60, "11010110": 45, "11101001": 20, "10011001": 5, "11001110": 5, "10011111": 26, "01010111": 5, "10100001": 62, "01100110": 102, "00110100": 25, "01100010": 22, "00010111": 78, "00011101": 22, "01000011": 7, "00111011": 4, "00000010": 59, "10101101": 11, "10001110": 22, "10110101": 7, "10110000": 64, "10111101": 22, "11010010": 17, "10000011": 4, "11111101": 32, "00000101": 25, "10101110": 23, "11101100": 38, "10101111": 8, "11011011": 16, "10100110": 39, "00110111": 4, "00101011": 4, "11111000": 18, "00010011": 52, "00000110": 21, "01010011": 1, "01010100": 6, "11101111": 22, "11110100": 13, "11000011": 11, "00001110": 12, "00100101": 25, "10110100": 14, "01101010": 94, "11101011": 14, "11110110": 17, "10100100": 42, "00110011": 91, "10110001": 33, "11011110": 3, "00111110": 4, "00010100": 21, "11001100": 24, "10111000": 12, "11000101": 5, "11000000": 119, "10110110": 22, "01001110": 16, "10010110": 6, "01110100": 49, "11100010": 16, "00011110": 2, "01011011": 9, "11100110": 83, "11001111": 2, "01111000": 18, "10010111": 78, "11100001": 43, "10000110": 44, "01110111": 20, "10111011": 154, "01011100": 10, "01110110": 1, "00000011": 13, "11000111": 39, "00010101": 8, "11101000": 98, "10100010": 69, "11111010": 18, "00110101": 31, "00011111": 2, "11100111": 18, "11010000": 92, "11101101": 15, "01100100": 44, "11000110": 26, "10011100": 22, "11010101": 10, "01110101": 10, "00011010": 11, "10111100": 22, "01011101": 6, "10000101": 4, "10101100": 37, "01000111": 16, "00100111": 24, "10111001": 83, "00110001": 62, "10100000": 16, "10000111": 2, "11010001": 13, "11001000": 36, "01101110": 22, "10010011": 26, "11101110": 61, "10001101": 11, "00001101": 8, "11010100": 3, "10111111": 21, "00001000": 23, "10110010": 4, "11010111": 20, "10001100": 40, "00000111": 9, "10000000": 19, "10110011": 11, "00110110": 39, "01101100": 35, "10100011": 12, "01011010": 7, "11111011": 24, "11111111": 32, "00101100": 22, "01001010": 21, "00011011": 30, "11011001": 13, "01100101": 39, "11100000": 9, "10110111": 112, "00100001": 15, "00011001": 24, "00001111": 2, "11110001": 28, "10001001": 6, "00000000": 2, "00100110": 15, "10000100": 12, "11110101": 16, "00010110": 6, "00111111": 56, "10001000": 10, "11110111": 10, "01111001": 10, "10011101": 23, "10010101": 13, "01101101": 4, "00100000": 47, "01101000": 31, "11100100": 17, "11100101": 13, "11111100": 16, "10011110": 3, "11011101": 11, "01000110": 2, "01110001": 37, "01001101": 10, "11000001": 95, "11111110": 23, "00101110": 22, "11110011": 13, "01001100": 48, "10111010": 6, "10101000": 1, "01100000": 93, "01011000": 1, "10100111": 25, "11000010": 58, "00010001": 5, "01000101": 9, "11110010": 6, "10010001": 23, "01010000": 5, "01000010": 1, "00001010": 3, "00101111": 2, "10000010": 30, "10101010": 22, "01110011": 4, "10011011": 8, "01001001": 8, "11111001": 10, "00100010": 73, "01010110": 17, "11011100": 6, "00010000": 4, "10111110": 8, "01000001": 2, "01101001": 8, "10101001": 12}, {"00101111": 1, "00111001": 5, "11010101": 3, "11100000": 9, "10000010": 4, "01111001": 2, "01010001": 6, "10111100": 8, "10100101": 3, "10111011": 3, "11000010": 3, "10111101": 4, "10001101": 5, "00001010": 7, "00111101": 4, "00100110": 12, "00011010": 17, "00011001": 4, "00110100": 9, "01111011": 8, "10110101": 3, "01101010": 1, "10110100": 3, "11110111": 10, "11110001": 4, "00001111": 11, "00110000": 15, "00000110": 6, "01101100": 5, "10100011": 21, "00101100": 3, "11111101": 8, "00101101": 2, "10010111": 27, "10011100": 3, "01010000": 7, "00011000": 22, "10001001": 18, "11001100": 19, "01100010": 4, "11011000": 14, "00100101": 15, "01001101": 1, "01110001": 3, "00010111": 24, "01010111": 5, "10100001": 22, "10011111": 17, "01010110": 1, "11111001": 4, "00100010": 43, "01100110": 36, "11101100": 35, "11001011": 18, "10101111": 5, "01100011": 16, "01101000": 22, "11101010": 115, "10111010": 9, "10001010": 16, "10101101": 10, "01110111": 40, "11010011": 32, "11011110": 55, "10110001": 15, "10101010": 9, "11000100": 38, "01100100": 24, "00001100": 1, "00100100": 31, "01111010": 17, "00010010": 4, "01000110": 31, "11000000": 47, "11000101": 16, "11110100": 35, "00101011": 5, "11111000": 22, "00010011": 35, "11100110": 28, "11001111": 58, "11100011": 30, "11110000": 5, "00010001": 61, "01101011": 11, "10010101": 33, "10011101": 33, "11011010": 18, "10001111": 49, "00110111": 7, "11100010": 23, "10010110": 9, "01110100": 12, "01001010": 3, "11011001": 10, "00011011": 64, "01000000": 9, "00011100": 66, "10111000": 9, "00010100": 18, "00111110": 2, "10001011": 12, "01001110": 56, "11011111": 64, "10000110": 2, "11100001": 6, "01111000": 10, "00101001": 6, "01100111": 22, "01010100": 5, "11101111": 54, "01010011": 7, "00100011": 19, "01001000": 32, "10011011": 71, "00101110": 39, "10011001": 1, "11001110": 169, "11101001": 18, "11010110": 7, "00110110": 27, "00111010": 1, "01001011": 27, "11000110": 4, "01000100": 112, "10010001": 12, "10111001": 3, "00100111": 30, "11110110": 25, "01011110": 2, "01010010": 11, "10010100": 8, "11100100": 121, "10000000": 14, "10110011": 47, "11001010": 5, "10011000": 18, "01011111": 84, "01011101": 7, "10101100": 6, "10000101": 12, "01000111": 2, "10101000": 3, "10100111": 7, "01100000": 78, "00001001": 15, "00001101": 66, "11100111": 14, "00011111": 24, "11100101": 29, "11101110": 55, "01010101": 123, "10110010": 19, "11010111": 47, "10001000": 35, "00111111": 111, "11010100": 15, "10111111": 25, "00001000": 31, "01011001": 9, "10100110": 9, "11011011": 89, "11011100": 7, "00010000": 6, "10111110": 8, "01000001": 8, "01111101": 18, "10000111": 4, "11010001": 41, "10100000": 46, "10100100": 66, "00110011": 49, "11011101": 17, "00011101": 26, "00110001": 13, "11110010": 37, "11000111": 2, "01110110": 22, "00010101": 18, "10110110": 8, "00000001": 9, "00101010": 9, "11001101": 8, "01000011": 18, "00000010": 27, "00111011": 26, "00000100": 60, "10001110": 10, "11111110": 43, "11000001": 32, "01101110": 20, "10010011": 7, "00101000": 9, "10011110": 44, "11111011": 19, "11111111": 5, "01011010": 19, "10101001": 8, "01101001": 2, "00011110": 11, "01011011": 23, "01000101": 10, "01001001": 1, "00111000": 10, "01100001": 21, "10110111": 4, "01101101": 5, "00100000": 16, "00000101": 12, "11111010": 3, "00110101": 12, "11001001": 12, "10100010": 8, "00000111": 11, "01101111": 11, "10001100": 22, "10011010": 17, "10101011": 6, "00110010": 14, "00100001": 11, "10110000": 18, "01111110": 9, "11010000": 22, "01110010": 10, "11110101": 6, "00010110": 13, "01110000": 19, "11101101": 14, "01000010": 8, "11001000": 30, "11110011": 17, "01001100": 32, "00001110": 5, "01001111": 3, "01100101": 10, "01111111": 7, "11111100": 9, "00001011": 10, "01111100": 10}, {"00010111": 1, "00111001": 1, "10110011": 2, "00101011": 1, "11111000": 3, "10100000": 2, "10010110": 1, "01110100": 1, "10000010": 2, "00101100": 1, "10010000": 1, "11010110": 1, "01111001": 3, "10001011": 1, "11011110": 5, "01011111": 2, "10110000": 5, "00010010": 1, "11000100": 1, "00000110": 1, "00101110": 2, "11101001": 6, "01100010": 5, "01111000": 7, "00100101": 8, "00110100": 2, "00101111": 3, "01100101": 1, "00001101": 3, "10010100": 6, "10100110": 4, "11011011": 3, "01000101": 7, "11110010": 15, "00110101": 14, "11111010": 14, "10010001": 9, "10111001": 18, "00011100": 6, "00101010": 14, "11110110": 2, "11101011": 13, "00101000": 13, "00001011": 7, "01101011": 12, "11010000": 6, "00110010": 15, "10101011": 2, "10100101": 10, "01011100": 1, "01111111": 1, "01001110": 19, "01110011": 1, "10101010": 11, "01100110": 19, "11111110": 3, "11000001": 4, "10110100": 5, "01101010": 24, "10000100": 33, "01111011": 15, "11100010": 29, "01010001": 28, "00001111": 2, "11110001": 38, "10001001": 7, "00000000": 10, "00000010": 4, "00111011": 28, "01000010": 31, "10110010": 10, "11010111": 35, "10001000": 1, "00111111": 34, "11111101": 34, "10001100": 4, "00000111": 42, "01101111": 27, "10010101": 11, "10011101": 47, "11011010": 28, "10000000": 11, "10111100": 17, "00100110": 18, "10000011": 42, "00101101": 40, "01010101": 11, "11001100": 63, "00010100": 11, "10111000": 26, "00111110": 6, "10111010": 1, "10001010": 52, "00111100": 23, "10010010": 33, "11111100": 10, "11001011": 32, "10101111": 8, "11101100": 21, "00000011": 1, "11000111": 6, "01110110": 20, "00010101": 64, "10111011": 41, "00011000": 11, "00001001": 14, "00001010": 46, "11101000": 73, "11110100": 32, "00010011": 39, "11100110": 48, "11001111": 7, "01000111": 8, "01011101": 43, "10000101": 7, "10101100": 12, "11101101": 11, "01110000": 7, "10110101": 18, "10001110": 5, "00000100": 14, "10000111": 1, "11010001": 9, "01101001": 4, "10101001": 28, "10111101": 95, "01011001": 10, "00011110": 4, "01011011": 3, "10011110": 43, "01101101": 1, "00100000": 13, "11001110": 66, "10011001": 180, "11011001": 57, "01001010": 50, "00011011": 131, "10100011": 8, "01101100": 27, "11011111": 19, "10011111": 52, "01010111": 4, "10100001": 2, "11100011": 13, "11110000": 31, "01000011": 23, "01001000": 14, "11110011": 2, "01001100": 27, "00100001": 31, "00011001": 18, "01111110": 37, "00011111": 16, "11100111": 4, "00011101": 59, "10100010": 22, "11001001": 30, "11011101": 43, "00100011": 11, "01010000": 11, "01100111": 19, "01010100": 9, "11101111": 5, "01010011": 16, "10110001": 59, "11000010": 44, "01110010": 34, "11100000": 38, "11010101": 21, "10011100": 23, "01100100": 37, "01010010": 17, "01011110": 26, "10110110": 23, "11101110": 29, "01000000": 31, "11111011": 6, "01011010": 24, "11111111": 72, "10101000": 9, "01011000": 17, "01100000": 69, "10100111": 33, "11101010": 19, "01101110": 7, "10010011": 15, "00010001": 22, "11011000": 29, "11000011": 15, "00001110": 50, "01001111": 26, "10011000": 10, "11001010": 15, "00111101": 18, "00110110": 11, "00111010": 2, "01001011": 15, "00011010": 11, "01110101": 20, "00010110": 32, "11110101": 22, "10010111": 25, "10001101": 26, "11100101": 40, "10100100": 24, "00110011": 35, "01000110": 30, "11000000": 5, "11000101": 15, "01110001": 76, "01001101": 2, "10110111": 48, "01100001": 6, "00101001": 38, "01110111": 6, "11010011": 6, "11100001": 21, "10000110": 10, "10101110": 24, "00000101": 6, "00110000": 32, "01101000": 67, "01100011": 40, "01001001": 21, "00111000": 36, "10001111": 38, "00110111": 16, "00110001": 11, "00100111": 12, "00001000": 10, "10111111": 10, "11010100": 12, "11100100": 11, "11001000": 17, "10111110": 8, "00010000": 10, "11011100": 9, "01000001": 9, "01111010": 11, "00100100": 17, "11001101": 17, "11010010": 17, "00000001": 7, "01010110": 11, "00100010": 23, "11111001": 27, "10011011": 1, "10000001": 1, "11000110": 3, "01000100": 25, "01111101": 11, "10101101": 17}, {"11010010": 1, "00001011": 2, "01001000": 1, "01011001": 2, "10110001": 2, "10110000": 2, "10010011": 2, "00011101": 2, "00001101": 1, "10001101": 2, "01001011": 3, "01100100": 13, "01100101": 12, "00100011": 1, "10111001": 2, "01111000": 3, "00001110": 5, "00101001": 9, "11011001": 11, "00011011": 5, "01001010": 2, "00010010": 18, "01111100": 5, "00100111": 7, "00101111": 11, "00100110": 12, "10010111": 10, "00000001": 9, "11110110": 7, "11101011": 2, "11001001": 4, "10100010": 3, "01011111": 6, "11101010": 5, "00000100": 5, "01000010": 18, "01000000": 14, "00110001": 16, "11111010": 4, "00110101": 3, "11011110": 6, "00110110": 8, "00101010": 11, "11001010": 14, "10011000": 1, "00111101": 5, "01001001": 3, "00111000": 10, "10011011": 11, "11111000": 1, "10011010": 3, "11001110": 3, "10011001": 1, "00110111": 27, "11111100": 13, "00111110": 16, "11001011": 16, "01101011": 25, "11011010": 31, "11100010": 25, "11101001": 1, "11010110": 6, "11110010": 21, "11101101": 8, "01110000": 7, "10101101": 76, "01000100": 2, "11000110": 16, "10111100": 90, "00011000": 6, "10111011": 33, "00010110": 1, "11110101": 36, "01010000": 27, "10100001": 1, "01010111": 59, "10100101": 45, "10000010": 78, "00101110": 66, "01010001": 17, "10111101": 12, "00110010": 1, "10101011": 7, "01101001": 2, "10101001": 34, "00001001": 5, "00010100": 24, "10111000": 38, "11001100": 5, "01000110": 18, "10011101": 23, "10010101": 64, "01001101": 8, "01110001": 3, "01100110": 21, "10011111": 19, "00010111": 9, "00110100": 5, "01101010": 15, "10110100": 70, "01000011": 47, "01011100": 6, "01111111": 16, "11001101": 13, "10110101": 53, "10001110": 32, "11111110": 23, "11000001": 17, "00010011": 31, "00000110": 70, "11110100": 14, "11010011": 94, "01110111": 8, "01101101": 6, "00100000": 19, "00101100": 21, "10010000": 11, "01001110": 9, "11101100": 50, "10101111": 27, "10110010": 13, "11010111": 84, "11100001": 12, "11011111": 47, "00100101": 3, "01001111": 11, "10000111": 26, "11010001": 79, "10100000": 20, "00101000": 36, "10000011": 5, "00011010": 2, "01110101": 36, "10101110": 123, "00000101": 12, "10110110": 37, "00000111": 2, "10001100": 6, "01101111": 6, "11111101": 58, "01110100": 19, "10010110": 29, "10101100": 7, "10000101": 27, "01011101": 12, "11010101": 20, "10011100": 1, "11100000": 5, "01111011": 123, "10000100": 54, "00010001": 33, "00000010": 21, "00111011": 27, "00001111": 5, "11110001": 26, "00000000": 14, "01011000": 1, "01100000": 5, "10101000": 19, "10100111": 57, "11110111": 61, "01100111": 29, "01111001": 25, "11101111": 19, "01010100": 15, "01010011": 24, "01000101": 14, "10111111": 34, "00001000": 106, "11010100": 37, "11100100": 52, "00001100": 2, "01111010": 27, "00100100": 17, "01110011": 84, "10101010": 70, "01101100": 41, "10100011": 14, "11110000": 14, "01110110": 25, "00010101": 31, "00000011": 12, "11000111": 6, "11100011": 17, "11100110": 28, "11001111": 7, "11101000": 30, "10110011": 17, "00111001": 15, "10000000": 12, "11000101": 15, "11000000": 2, "11100101": 16, "00001010": 17, "11100111": 7, "00011111": 5, "10001111": 6, "11011011": 12, "10100110": 7, "01010101": 68, "00101101": 27, "00111111": 34, "10001000": 2, "00011001": 2, "00100001": 12, "01011011": 68, "00011110": 5, "01110010": 13, "11000010": 11, "10001010": 9, "10111010": 19, "10110111": 17, "01100001": 12, "10010100": 28, "00111100": 22, "11010000": 18, "01111110": 8, "01101110": 14, "10011110": 8, "10100100": 4, "00110011": 28, "11000100": 44, "11011000": 5, "01100011": 11, "01101000": 36, "00100010": 31, "11111001": 7, "10000001": 10, "10010001": 34, "10111110": 18, "11011100": 17, "00010000": 26, "01000001": 32, "01011010": 6, "11111011": 42, "11111111": 17, "01001100": 2, "11110011": 2, "11011101": 24, "00110000": 10, "01010010": 42, "01011110": 31, "01111101": 4, "10001011": 5, "10010010": 2}, {"11000010": 1, "10101101": 1, "01100111": 1, "00101110": 2, "10001101": 1, "11101101": 2, "00100011": 7, "11101001": 1, "00111100": 1, "10110011": 5, "11101000": 3, "01100110": 2, "11001011": 3, "00100111": 2, "00000110": 5, "10111010": 3, "10001010": 5, "11100010": 4, "11010000": 4, "00101101": 2, "11011010": 3, "10011010": 2, "11001001": 1, "10100010": 2, "01100100": 15, "00011000": 4, "10111100": 2, "11001100": 17, "00100001": 2, "01000110": 6, "00100010": 8, "01010110": 3, "11111001": 13, "00110110": 3, "10001011": 4, "10010100": 5, "10111011": 24, "11100101": 10, "00011100": 8, "11111000": 1, "00101011": 13, "01000011": 81, "10100101": 28, "10000010": 12, "11011110": 8, "11110011": 2, "01001100": 12, "00110111": 20, "10001111": 5, "10010010": 41, "11111100": 3, "01000100": 6, "11000110": 77, "00010010": 11, "11110100": 3, "00010011": 64, "01101011": 23, "00110100": 32, "00010111": 17, "01100010": 16, "10011111": 8, "00111001": 32, "10000000": 14, "10000100": 37, "01111011": 3, "01001000": 33, "10110101": 122, "10001110": 6, "11101010": 13, "01100011": 18, "01101000": 46, "00111000": 3, "01000101": 2, "11101110": 14, "10100011": 7, "01101100": 10, "00101010": 43, "11001101": 24, "01101111": 3, "10001100": 14, "00000111": 15, "10001000": 6, "00111111": 27, "01111101": 37, "00100101": 25, "01001111": 12, "10011000": 8, "11001010": 57, "11000011": 4, "00001110": 6, "01101110": 38, "10010011": 53, "10111101": 63, "01011001": 32, "00110010": 6, "10101011": 7, "10010111": 4, "00010110": 16, "11110101": 32, "11010001": 1, "10000111": 11, "11010101": 4, "01110101": 8, "00011010": 13, "01000000": 9, "11111011": 50, "01011010": 19, "11111111": 10, "01001011": 17, "00111010": 18, "11000001": 2, "11111110": 5, "11010110": 7, "11100100": 26, "10111111": 5, "00001000": 11, "11010100": 34, "01110010": 20, "11000100": 14, "10100001": 35, "01010111": 61, "01010000": 18, "10110010": 8, "01101001": 1, "00011110": 8, "01011011": 25, "10110110": 13, "11101111": 13, "01010100": 2, "01010011": 8, "11110111": 92, "01111001": 13, "01011100": 2, "01111111": 70, "00111110": 1, "00010100": 25, "01000010": 190, "10101010": 1, "01110011": 21, "01110111": 60, "11010011": 13, "11110110": 23, "00000001": 12, "01011111": 16, "10100111": 14, "10101000": 20, "01100000": 90, "00001001": 2, "00001101": 13, "00110101": 3, "10101110": 58, "00000101": 24, "00011101": 46, "10010001": 70, "10000001": 10, "10110000": 36, "00011001": 55, "11010010": 12, "00000000": 4, "10001001": 9, "11011111": 79, "10000110": 2, "11100001": 1, "01010101": 6, "01011101": 6, "10000101": 6, "01000111": 3, "10101100": 8, "01110000": 5, "10011011": 27, "01001110": 12, "11001000": 84, "10111001": 16, "10010000": 9, "00101100": 20, "00111101": 24, "11001110": 49, "10011001": 67, "10011101": 17, "10010101": 37, "11011101": 29, "10110111": 40, "00001010": 22, "11100111": 21, "00011111": 11, "01111010": 22, "00001100": 70, "00100100": 165, "00110001": 25, "11001111": 5, "11100110": 20, "10101111": 37, "10100100": 18, "10000011": 53, "11100000": 16, "10110100": 23, "01101010": 86, "01110001": 52, "01001101": 6, "11000000": 3, "11000101": 32, "11111101": 41, "11100011": 20, "00100110": 11, "01010001": 29, "01001010": 23, "00011011": 91, "11011001": 15, "00101001": 6, "10100110": 42, "11011011": 10, "01000001": 17, "11011100": 15, "00010000": 5, "10111110": 29, "00001011": 11, "11110010": 20, "00101000": 22, "01110110": 1, "00000011": 9, "11000111": 11, "00010101": 21, "00001111": 3, "11110001": 15, "00000010": 26, "00111011": 10, "10011110": 13, "00110000": 1, "10010110": 9, "01110100": 3, "00100000": 73, "01101101": 1, "01010010": 85, "01011110": 12, "10100000": 18, "01100101": 5}, {"00101111": 1, "00101001": 1, "10100000": 1, "00010010": 2, "00000101": 2, "00011000": 5, "01001101": 2, "01110001": 2, "11010011": 3, "01111110": 2, "11011101": 4, "00001001": 2, "01011001": 6, "11111101": 1, "00111110": 1, "11100101": 5, "10101110": 12, "11001101": 3, "11011010": 7, "01101101": 1, "11110100": 4, "00111010": 2, "01001011": 7, "11010001": 3, "10000111": 1, "00101110": 16, "10010100": 4, "01010101": 4, "10011010": 3, "11101000": 7, "11000000": 1, "11000101": 16, "01111000": 17, "00001011": 11, "10000001": 8, "00101101": 13, "10100100": 7, "00110011": 9, "01000011": 6, "11010110": 4, "01010000": 6, "00011101": 20, "01110010": 25, "11010000": 4, "10011011": 5, "00010011": 13, "00000110": 6, "00100110": 36, "01100111": 29, "01111001": 17, "11110111": 26, "00000000": 2, "10001001": 28, "11010010": 15, "01110000": 23, "11101101": 1, "00110110": 10, "01011011": 2, "00011110": 14, "10110001": 16, "11010111": 1, "10110010": 25, "00100001": 58, "00011001": 150, "01101011": 15, "11100010": 46, "10010110": 3, "01110100": 32, "01110111": 11, "10111011": 15, "00000011": 1, "11000111": 3, "00010101": 29, "01110110": 26, "10101111": 29, "11101100": 73, "11001011": 9, "10000100": 6, "10001101": 13, "10010010": 27, "11111100": 6, "01000000": 46, "10010111": 27, "00010110": 16, "11110101": 11, "01010010": 3, "01011110": 16, "10101101": 10, "11011111": 86, "00101011": 2, "10000110": 25, "11100001": 7, "10011101": 11, "10010101": 54, "11001110": 27, "10011001": 161, "10110000": 15, "01001010": 59, "00011011": 36, "11011001": 70, "00111001": 12, "10110011": 47, "10000000": 21, "00001010": 12, "01001000": 89, "11000010": 79, "11110010": 46, "01100100": 20, "11101111": 17, "01010011": 8, "01010100": 8, "10011100": 24, "11010101": 4, "01011100": 2, "01111111": 23, "10001000": 5, "00111111": 68, "11000100": 61, "00110001": 110, "00110000": 62, "01000110": 34, "01100001": 29, "10110111": 84, "10101000": 3, "01011000": 46, "01100000": 45, "10100111": 12, "01100010": 67, "01100110": 52, "00110100": 14, "00010111": 24, "10011111": 39, "01010111": 7, "10100001": 14, "10010001": 21, "11000110": 11, "01000100": 6, "11011011": 3, "10100110": 12, "00110111": 59, "10001111": 25, "10111001": 13, "00100111": 9, "11101010": 49, "01100011": 23, "01101000": 20, "01001110": 42, "10010000": 9, "10000010": 12, "10100101": 39, "10100011": 19, "01101100": 33, "10111101": 7, "00000010": 4, "00111011": 36, "01111101": 13, "00100101": 13, "10011000": 20, "11001010": 36, "11000011": 13, "00001110": 38, "01001111": 15, "11100000": 21, "11100100": 87, "10111111": 4, "00001000": 36, "11010100": 12, "00000100": 3, "10110101": 33, "10001110": 16, "11111110": 21, "11000001": 1, "00100011": 1, "11101110": 23, "11011000": 6, "11011100": 1, "01000001": 3, "10111110": 21, "00010000": 10, "01010001": 16, "10111000": 6, "00011100": 6, "00010100": 3, "11001100": 37, "11110011": 37, "01001100": 44, "01011111": 22, "10111100": 14, "10000101": 2, "10101100": 12, "01011101": 33, "01000111": 9, "10000011": 20, "10110100": 37, "01101010": 32, "01101110": 30, "10010011": 40, "11100110": 35, "00001101": 15, "00001100": 1, "01111010": 25, "00100100": 31, "01110011": 5, "10101010": 16, "11111010": 2, "00110101": 42, "11001001": 9, "10100010": 37, "01100101": 29, "10110110": 12, "11101011": 1, "11110110": 22, "01000101": 8, "00111000": 1, "01001001": 36, "10111010": 5, "10001010": 40, "00110010": 1, "10101011": 6, "01000010": 19, "00000001": 8, "00111100": 25, "01101111": 5, "00000111": 14, "10001100": 17, "00011111": 58, "11100111": 20, "11001000": 22, "00101000": 19, "10101001": 9, "01101001": 15, "00011010": 9, "01110101": 16, "00100010": 1, "11111001": 9, "01010110": 8, "11100011": 35, "11110000": 3, "11111111": 1, "01011010": 9, "11111011": 7, "00010001": 12, "11110001": 2, "00001111": 7, "10011110": 20}, {"10000100": 1, "00010100": 1, "10111100": 1, "10111000": 1, "00001010": 1, "00001101": 1, "10010100": 2, "11111001": 1, "01010110": 1, "10010010": 2, "10010110": 2, "10000011": 1, "11010101": 3, "11101010": 3, "11011010": 7, "00111110": 3, "01101001": 3, "01100111": 2, "01001110": 5, "10101101": 1, "00100110": 2, "00101010": 4, "01111001": 6, "10001101": 1, "01010001": 3, "00111100": 7, "00110100": 11, "11111110": 4, "11000001": 8, "10001011": 5, "10001111": 2, "11111100": 8, "00110001": 6, "01000110": 5, "01011101": 2, "01000111": 1, "10000101": 3, "10111101": 5, "11101100": 5, "10110011": 16, "00101011": 5, "11111000": 2, "00111101": 11, "00101001": 9, "00000001": 6, "01111000": 4, "10111001": 3, "10010011": 14, "00111011": 8, "00000010": 3, "11010000": 8, "11010011": 10, "01110111": 17, "10110101": 29, "00000100": 18, "10001110": 55, "11110111": 37, "10000110": 3, "11100001": 25, "11011111": 20, "10111011": 28, "00011000": 14, "10110010": 47, "11100010": 49, "11110010": 28, "00111001": 11, "10000000": 10, "11110110": 4, "11101011": 2, "10110001": 105, "11011110": 45, "01011011": 15, "00011110": 25, "00110110": 10, "10101010": 5, "01110011": 25, "11111101": 12, "10010111": 60, "00010110": 1, "11110101": 8, "00110000": 14, "00101111": 3, "11111010": 3, "00110101": 90, "00011111": 88, "11100111": 4, "10010001": 32, "11000110": 6, "01000100": 1, "10000001": 5, "01100010": 146, "01100110": 33, "10100001": 20, "00010111": 29, "10011111": 49, "11110100": 40, "00010011": 38, "00000110": 9, "01010100": 10, "01010011": 25, "11101111": 4, "00010001": 3, "11010110": 14, "11011011": 7, "10100110": 14, "00110111": 26, "10000111": 1, "11010001": 8, "11110001": 1, "00001111": 28, "11001000": 58, "00100101": 16, "01001111": 12, "10011000": 3, "11001010": 8, "11000011": 4, "00001110": 4, "00101100": 13, "10010000": 5, "01000011": 3, "11100000": 23, "11000101": 3, "11000000": 17, "11001100": 91, "00011101": 68, "11011101": 2, "11100100": 115, "10011011": 24, "10001010": 23, "10111010": 9, "00100011": 51, "01010000": 15, "01100001": 21, "10110111": 81, "10110110": 47, "01101100": 19, "10100011": 49, "01100011": 18, "01101000": 60, "01000000": 38, "10110100": 7, "01101010": 29, "11001110": 165, "10011001": 220, "00101000": 25, "10100100": 37, "00110011": 25, "01110001": 44, "01001101": 43, "11001011": 12, "10101111": 11, "11101000": 13, "11000100": 44, "00100111": 17, "00000000": 33, "10001001": 6, "11010010": 7, "11001111": 33, "11100110": 28, "11011000": 46, "01011001": 10, "00000101": 5, "01100100": 38, "00001100": 46, "00100100": 6, "01111010": 1, "10100010": 11, "11001001": 58, "00111111": 33, "10001000": 33, "01011111": 55, "01001000": 39, "11001101": 16, "00101101": 13, "10011010": 5, "00001001": 7, "01011000": 30, "10100111": 42, "10101000": 10, "01100000": 5, "11101110": 16, "10110000": 20, "01000010": 13, "01001001": 24, "00111000": 9, "01000101": 13, "01001100": 96, "11110011": 24, "10011110": 3, "01110010": 16, "11000010": 8, "01010010": 4, "01011110": 12, "10010101": 11, "10011101": 12, "11111111": 3, "11111011": 25, "01011010": 15, "01110101": 9, "00011010": 29, "00000011": 3, "01110110": 3, "00010101": 30, "11000111": 17, "11100011": 28, "11110000": 10, "00110010": 48, "10101011": 9, "10000010": 5, "10100101": 10, "10100000": 13, "01111100": 7, "01101101": 2, "00100000": 8, "00000111": 5, "10001100": 14, "11100101": 25, "01001010": 179, "00011011": 19, "11011001": 25, "01001011": 27, "00111010": 7, "01110000": 20, "11101101": 4, "01011100": 43, "01111111": 8, "00010000": 4, "11011100": 13, "10111110": 13, "01000001": 4, "00001011": 47, "00100001": 12, "00011001": 28, "01111101": 2, "01111011": 17, "11010100": 4, "00001000": 25, "10111111": 4}, {"10111100": 1, "00010010": 1, "00000100": 1, "10101111": 2, "11010001": 1, "10000111": 1, "01110111": 2, "01111001": 5, "10010011": 3, "10110101": 1, "11011111": 9, "11010000": 3, "01010000": 2, "01010101": 6, "00110110": 10, "00111001": 7, "10011010": 9, "10111101": 3, "10101011": 4, "00111011": 3, "00000010": 2, "00000110": 5, "01111000": 4, "11000010": 8, "11111100": 6, "00101011": 1, "11111000": 2, "00101111": 3, "00101110": 4, "11000101": 11, "11000000": 19, "11011010": 5, "11010010": 2, "11101001": 3, "01110000": 11, "00111101": 1, "10101001": 1, "01101001": 7, "00101000": 4, "00111110": 6, "10100110": 4, "10100101": 2, "11110101": 1, "00010110": 8, "11100011": 28, "10010100": 1, "01010001": 8, "01000000": 39, "11100010": 43, "00001001": 12, "11100110": 25, "11001111": 30, "11010110": 7, "01001110": 35, "11010011": 7, "11100001": 2, "10000110": 26, "00110001": 7, "00110000": 42, "10011100": 11, "01110010": 66, "10001000": 7, "00111111": 52, "11010100": 19, "10111111": 56, "00001000": 16, "01011100": 5, "01111111": 18, "00001010": 15, "00010100": 9, "11001100": 61, "01011000": 6, "10101000": 2, "01100000": 21, "10100111": 35, "01110100": 2, "10010110": 4, "00100001": 28, "00011001": 79, "00101001": 28, "11101110": 21, "01101101": 11, "00100000": 19, "11100101": 7, "11001110": 58, "10011001": 296, "11010111": 6, "10110010": 2, "11110000": 4, "01001000": 83, "10011011": 30, "00110100": 49, "00010111": 99, "01100010": 95, "10011111": 17, "01100110": 15, "00010011": 26, "01010100": 13, "11101111": 14, "11110100": 8, "10101110": 34, "00000101": 7, "10000001": 1, "10010001": 17, "00100101": 32, "01001111": 10, "11000011": 1, "00001110": 13, "01111011": 7, "10000100": 5, "11000100": 90, "11101000": 16, "10100010": 9, "11100000": 37, "10001110": 35, "11111110": 12, "11000001": 4, "00010001": 3, "11001000": 71, "01101110": 5, "01000010": 13, "00011111": 107, "11100111": 19, "01111110": 4, "01110101": 35, "00011000": 17, "10111011": 1, "10100100": 4, "00110011": 111, "01000101": 10, "00000001": 10, "00100010": 33, "11111001": 5, "01101011": 4, "10010101": 11, "10011101": 27, "11100100": 141, "00011101": 104, "10110011": 108, "11001010": 85, "10011000": 20, "11011101": 17, "00111100": 26, "11011001": 34, "01001010": 190, "00011011": 26, "01100011": 57, "01101000": 24, "11101010": 19, "01001100": 66, "10010111": 103, "01011001": 36, "11101101": 10, "01000111": 2, "10000101": 1, "01011101": 19, "10101100": 6, "00001111": 16, "11110001": 33, "10110001": 67, "11011110": 33, "10001010": 31, "10111010": 6, "10110111": 57, "01100001": 13, "01000001": 1, "11011100": 2, "00010000": 11, "10111110": 3, "10101101": 3, "00101100": 4, "11001011": 11, "11101100": 15, "10110110": 30, "00001100": 17, "00100100": 33, "10110000": 32, "01011111": 7, "11110010": 28, "01110001": 15, "01001101": 8, "01000110": 4, "10001101": 7, "01011010": 4, "11111111": 18, "11111011": 7, "01100100": 81, "01000100": 49, "11000110": 27, "11110111": 18, "00101101": 22, "00111000": 11, "01001001": 6, "10101010": 8, "01110011": 12, "01111101": 13, "01111100": 11, "00111010": 1, "01001011": 7, "10110100": 5, "01101010": 10, "10001111": 4, "00110111": 12, "10100011": 5, "01101100": 20, "01010010": 3, "01011110": 5, "11101011": 3, "11110110": 15, "11001101": 4, "00101010": 7, "00110101": 103, "11111010": 2, "00011110": 15, "01011011": 2, "10100001": 40, "01010111": 23, "11000111": 8, "00010101": 4, "00000011": 2, "10001011": 6, "10010010": 14, "10011110": 9, "10000011": 9, "10000010": 8, "10100000": 4, "10001001": 17, "00100111": 7, "10001100": 6, "00000111": 10, "01101111": 3}, {"01110010": 3, "11101101": 1, "01010101": 2, "00000001": 1, "11001011": 1, "00100110": 1, "10000100": 2, "01011100": 2, "01111101": 1, "11110000": 1, "00100111": 1, "01000010": 3, "11010010": 3, "10100000": 2, "01101011": 1, "00000110": 6, "01000011": 3, "11101100": 5, "10110011": 3, "00101110": 2, "11011010": 3, "11111100": 1, "01110111": 7, "11100000": 3, "11011110": 5, "01000110": 2, "00011100": 3, "01001111": 1, "00010010": 3, "11011000": 7, "00110110": 2, "11010011": 6, "11110110": 2, "11101011": 2, "11100001": 5, "10000110": 3, "10010110": 9, "01110100": 4, "11001111": 5, "10010100": 5, "10011100": 1, "11101000": 8, "01011001": 15, "10001011": 4, "00001100": 1, "01111010": 5, "00100100": 8, "00000100": 14, "11111101": 9, "10011011": 8, "10111100": 3, "00010100": 11, "10110001": 7, "11011111": 7, "11010101": 4, "10001110": 17, "10110101": 16, "11000001": 14, "00101101": 4, "00110010": 4, "10101011": 29, "00010011": 34, "11110100": 21, "00101011": 6, "11111000": 19, "10011110": 42, "01010001": 24, "00110001": 9, "01011111": 52, "01111011": 15, "10010010": 15, "10111001": 86, "11101110": 128, "00001010": 86, "11011101": 32, "00010111": 128, "10011111": 78, "01100010": 43, "00110100": 13, "01100110": 26, "01001101": 2, "01110001": 13, "01000000": 4, "10000011": 11, "10100100": 14, "00110011": 26, "01110101": 18, "00011010": 24, "00001011": 15, "10110000": 4, "01001010": 127, "00011011": 174, "11011001": 106, "00000010": 18, "10101101": 4, "10001000": 6, "00111111": 9, "01001110": 39, "00101100": 22, "10010000": 17, "00111010": 10, "01001011": 36, "11101010": 49, "01100011": 4, "01101000": 33, "00110000": 29, "00101111": 6, "11100110": 33, "11110011": 28, "01001100": 19, "11000010": 17, "10110110": 29, "11100011": 20, "10011001": 28, "11001110": 15, "00001110": 5, "11000011": 2, "11101001": 7, "11010110": 3, "01111000": 21, "00101001": 6, "10101111": 47, "00111100": 7, "10111010": 31, "10110111": 2, "01100001": 3, "00100001": 33, "00011001": 80, "00111001": 25, "10000000": 8, "11001000": 10, "00100101": 15, "10011000": 27, "11001010": 11, "01101110": 22, "10010011": 17, "10010001": 60, "10000001": 11, "00011111": 293, "11100111": 7, "01111110": 8, "11010000": 18, "10010101": 9, "10011101": 5, "11110111": 13, "01100111": 12, "01111001": 31, "10101110": 17, "00000101": 8, "00100010": 7, "01010110": 4, "11111001": 40, "10001111": 54, "00110111": 7, "11011011": 19, "10100110": 21, "10010111": 57, "00010110": 7, "11110101": 7, "00000000": 11, "10001001": 25, "00000111": 3, "01101111": 5, "00001001": 25, "01010011": 30, "01010100": 18, "00111101": 47, "11100101": 23, "10100101": 15, "10000010": 5, "00111110": 10, "10111000": 20, "11001100": 34, "01001001": 35, "00111000": 12, "01000101": 18, "10101010": 16, "01110011": 11, "11010111": 36, "10110010": 57, "01011110": 2, "01010010": 2, "11000111": 1, "00000011": 2, "01110110": 14, "00010101": 14, "00011000": 32, "01100100": 33, "01000100": 8, "11000110": 43, "11100100": 58, "10111111": 16, "00001000": 10, "11010100": 13, "01100000": 1, "01011000": 32, "10101000": 24, "10100111": 25, "10000111": 13, "11010001": 17, "00100000": 3, "01101101": 16, "11100010": 56, "01111100": 18, "00011101": 58, "01001000": 15, "11001001": 8, "10100010": 19, "11111010": 1, "00110101": 6, "11111111": 54, "01011010": 45, "11111011": 27, "01101001": 18, "10101001": 27, "11000101": 25, "11000000": 18, "00100011": 5, "01010000": 14, "10100001": 5, "01010111": 18, "01011011": 54, "00011110": 19, "11110010": 14, "10110100": 8, "01101010": 23, "00010001": 74, "10101100": 1, "01000111": 2, "10000101": 4, "01011101": 30, "10011010": 4, "11001101": 4, "00101010": 8, "00101000": 26, "01110000": 3, "10111110": 50, "11011100": 4, "01000001": 7, "10100011": 42, "01101100": 16, "00001101": 7, "00001111": 26, "11110001": 9, "11000100": 19}, {"01100111": 1, "00010001": 4, "10001101": 3, "00100001": 5, "10111101": 2, "00110000": 1, "11101001": 1, "00101000": 2, "01101101": 2, "11100101": 3, "11101101": 1, "00000110": 4, "11010000": 3, "11011000": 3, "00010010": 2, "11011101": 7, "01010001": 4, "10100000": 3, "00111110": 7, "10101001": 5, "11111000": 1, "10010100": 7, "11100011": 5, "10001100": 8, "00000111": 4, "01101111": 3, "00110110": 3, "00001011": 6, "00100111": 8, "00101110": 8, "01111101": 6, "11010101": 6, "00110001": 4, "11010010": 1, "00000100": 2, "01111001": 12, "11010110": 2, "01111111": 8, "10011100": 3, "01110010": 2, "10000100": 7, "00101010": 2, "01111110": 2, "01010101": 15, "01000011": 11, "00101001": 11, "01111000": 3, "01110001": 9, "01100010": 105, "01100110": 47, "00110100": 23, "10011111": 23, "00010111": 52, "01100100": 35, "00111101": 13, "00110010": 2, "10101011": 6, "00010011": 52, "11110100": 1, "01010100": 4, "01010011": 5, "11101111": 13, "10011110": 46, "01010000": 14, "10100001": 9, "01010111": 8, "11011010": 8, "00101101": 19, "10110001": 150, "11011110": 5, "11110110": 3, "11101011": 7, "10111001": 32, "00110111": 126, "10001111": 34, "10010110": 42, "01110111": 16, "01111010": 3, "00100100": 3, "00001100": 10, "11100001": 4, "10000110": 12, "11010011": 8, "10100011": 28, "01101100": 106, "00101100": 3, "10010000": 18, "01001110": 40, "11101100": 159, "11001011": 7, "10101111": 8, "11000001": 8, "11111110": 17, "00011100": 51, "11001100": 87, "10111000": 7, "00010100": 22, "10001001": 27, "00000000": 5, "11110001": 2, "00001111": 16, "11010100": 1, "00001000": 3, "10111111": 17, "11000011": 3, "00001110": 40, "00100101": 20, "01001111": 4, "00000101": 18, "10101110": 10, "11100100": 139, "10110011": 10, "11001010": 65, "10011000": 26, "10000000": 7, "11100010": 142, "10011011": 4, "01001000": 44, "11000110": 33, "01000100": 87, "10010001": 51, "10000001": 18, "00011000": 29, "10111011": 37, "01001010": 29, "00011011": 31, "11011001": 29, "11000100": 79, "11101000": 32, "01011110": 4, "01010010": 9, "11001110": 81, "10011001": 175, "10011101": 4, "10010101": 10, "10101101": 6, "00111011": 25, "00000010": 10, "11111010": 12, "00110101": 83, "11001001": 7, "10100010": 1, "10010111": 9, "11010001": 11, "10000111": 33, "00010110": 5, "11110101": 10, "10101000": 5, "01011000": 27, "10100111": 20, "01100000": 40, "00001001": 20, "00001101": 69, "10111100": 7, "01011111": 25, "00011001": 47, "11001101": 17, "10011010": 20, "10001000": 1, "00111111": 132, "10110010": 16, "11010111": 10, "10100110": 17, "11011011": 38, "01000001": 9, "00010000": 10, "11011100": 24, "10111110": 10, "01101110": 17, "10010011": 8, "01110000": 5, "01000111": 2, "01011101": 44, "10000101": 10, "10101100": 12, "01110110": 1, "00010101": 21, "11000111": 2, "00000011": 2, "11100110": 63, "11001111": 3, "11100000": 41, "00011101": 35, "01101000": 2, "01100011": 3, "00101111": 4, "00000001": 5, "01010110": 2, "00100010": 26, "11111001": 14, "11111101": 16, "11110011": 3, "01001100": 20, "11110111": 22, "11000010": 13, "10010010": 22, "11101110": 16, "01000110": 10, "10100101": 18, "10000010": 5, "11000000": 62, "00011010": 8, "01110101": 8, "01000010": 34, "01110011": 10, "10101010": 7, "11101010": 22, "10000011": 21, "00110011": 49, "10100100": 16, "00111100": 17, "01011001": 15, "01101010": 65, "10110100": 18, "00011111": 4, "11100111": 3, "10110101": 17, "10001110": 21, "10110111": 68, "01100001": 6, "10001010": 4, "10111010": 10, "01001001": 20, "00111000": 19, "11111111": 4, "01011010": 20, "11111011": 8, "00001010": 19, "11110010": 5, "10110110": 12, "01001011": 12, "11110000": 2, "11011111": 26, "01000000": 4, "00100110": 4, "10001011": 13, "10110000": 8, "00011110": 20, "01011011": 2, "11001000": 10}, {"10000100": 2, "11010011": 1, "01101001": 1, "10101001": 1, "10001101": 1, "11010110": 5, "10011100": 1, "01000101": 1, "00101110": 1, "11101101": 2, "00111100": 6, "00101101": 4, "01110000": 6, "10100000": 3, "10111101": 3, "00000101": 4, "00101111": 5, "10110000": 5, "10000011": 2, "01111000": 4, "00101010": 2, "01111011": 3, "00010011": 3, "10000110": 9, "11010001": 5, "10000111": 4, "10111100": 3, "11001101": 4, "10101100": 2, "01011101": 3, "01000111": 2, "00000100": 5, "00000001": 7, "10010010": 4, "11101001": 2, "10000010": 4, "11111101": 4, "10111001": 16, "00100111": 17, "11111100": 4, "11011111": 40, "00110101": 41, "10100010": 20, "11110010": 12, "01000000": 13, "00110000": 37, "01000011": 9, "00011000": 16, "10111011": 19, "11100000": 16, "00110111": 69, "10001111": 18, "00100001": 33, "00011001": 160, "01100001": 9, "10110111": 19, "01111110": 9, "11010000": 3, "11000110": 11, "01000100": 10, "10010001": 52, "01011111": 52, "00001001": 29, "11011101": 25, "10110011": 83, "00111001": 5, "10000000": 3, "10101101": 2, "11001000": 18, "00100101": 6, "10011000": 15, "11001010": 14, "00001110": 15, "01001111": 6, "11110100": 92, "00101011": 1, "11111000": 5, "00111101": 50, "01100010": 22, "10011111": 60, "00010111": 12, "00110100": 6, "01100110": 8, "11000010": 53, "01110010": 6, "10110001": 34, "00011110": 10, "01101011": 10, "10010101": 13, "10011101": 68, "11011010": 8, "00101100": 23, "01001000": 133, "11001100": 134, "00010100": 12, "00111110": 3, "01100101": 68, "11110111": 40, "01111001": 29, "01010100": 1, "01010011": 2, "01100111": 6, "10111111": 5, "11010100": 2, "00001000": 38, "00111111": 31, "10001100": 7, "01101111": 13, "00000111": 8, "11100111": 3, "00011111": 120, "00001010": 34, "11000100": 103, "01000010": 126, "00110001": 46, "10010110": 10, "01110100": 76, "11100010": 3, "11100100": 298, "11101010": 55, "01100011": 8, "01101000": 17, "01001110": 39, "00110110": 23, "11100101": 86, "00101001": 21, "10010011": 18, "01101110": 13, "00100011": 9, "10100001": 7, "01010111": 17, "11110011": 7, "01001100": 25, "01011000": 6, "10100111": 20, "01100000": 50, "10101000": 2, "01011001": 40, "00100000": 5, "01101101": 13, "11010111": 15, "10110010": 11, "01011110": 10, "01010010": 5, "00010001": 21, "10110101": 52, "10011110": 16, "01111101": 1, "11001011": 12, "11101100": 12, "10101111": 18, "00010110": 11, "11110101": 39, "00101000": 10, "11100110": 35, "00001011": 2, "11101000": 6, "10100101": 12, "01110001": 18, "01001101": 22, "01000110": 28, "01001010": 150, "11011001": 55, "00011011": 14, "11111011": 1, "11111111": 39, "01011010": 12, "11100011": 15, "00000011": 3, "00010101": 32, "01110110": 9, "11000111": 6, "01100100": 54, "00010010": 6, "01010001": 18, "00001111": 9, "11110001": 2, "10001001": 14, "01110111": 22, "01111010": 7, "00100100": 30, "00001100": 30, "11101011": 1, "11110110": 9, "11101110": 19, "11000101": 1, "11000000": 14, "00100110": 2, "10101110": 1, "00110010": 6, "10101011": 2, "10100100": 19, "00110011": 18, "01011100": 15, "01111111": 16, "10011001": 294, "11001110": 10, "10110110": 16, "11011000": 5, "00011101": 10, "10100011": 14, "01101100": 9, "00011010": 4, "01110101": 7, "10100110": 1, "11011011": 8, "11011100": 3, "00010000": 8, "10111110": 31, "10101010": 1, "01110011": 14, "01111100": 14, "01010110": 1, "00100010": 15, "11111001": 5, "01101010": 76, "10110100": 14, "01001001": 3, "00111000": 24, "10001010": 1, "10111010": 5, "11000001": 2, "11111110": 6, "01001011": 13, "00111010": 3, "10011011": 13}, {"01000011": 1, "00000110": 1, "01000100": 1, "11000110": 1, "01111011": 4, "10000100": 2, "00000101": 2, "00100101": 2, "00110100": 2, "11010101": 1, "10010011": 5, "00101111": 5, "01011001": 6, "00010010": 2, "11010000": 8, "01100110": 1, "11000000": 2, "11000101": 4, "00101001": 5, "11101101": 3, "01010101": 3, "00101110": 1, "10100000": 3, "11011111": 6, "00100110": 2, "10111000": 2, "11111000": 2, "00101011": 1, "00101101": 2, "11001000": 7, "11101110": 6, "10000011": 2, "11101010": 4, "10101101": 1, "11100000": 5, "00000001": 7, "00111100": 7, "00110110": 9, "11111100": 4, "11010001": 3, "01000101": 20, "01011111": 11, "10001110": 12, "10011010": 1, "11110001": 3, "00001111": 12, "11110101": 3, "00010110": 8, "11110111": 8, "11001011": 5, "11101100": 31, "01000110": 25, "01001110": 39, "01000111": 3, "01011101": 18, "10000101": 5, "11000001": 11, "11111110": 8, "00001010": 7, "11000011": 1, "00001110": 17, "01001111": 12, "10110100": 3, "01101010": 29, "11010111": 1, "10110010": 36, "01110100": 72, "11100010": 33, "11100100": 39, "00111011": 3, "00000010": 12, "00100011": 8, "00001011": 27, "11111101": 6, "11101001": 5, "11010110": 7, "10010111": 45, "00010011": 35, "11110100": 68, "00110001": 44, "00110000": 20, "11001100": 71, "00111110": 12, "00010100": 6, "01100101": 89, "01110111": 41, "01111110": 4, "00011111": 183, "11100111": 39, "10110110": 20, "10110101": 99, "00000100": 25, "11101000": 5, "11000100": 23, "11111010": 5, "00110101": 41, "00011101": 89, "10110011": 230, "00111001": 39, "11001010": 50, "10011000": 7, "10000000": 12, "10100010": 31, "11001001": 24, "11000010": 31, "01110010": 18, "10110001": 59, "11011110": 17, "01011011": 9, "00011110": 14, "11100110": 49, "11001111": 17, "01101100": 9, "10100011": 60, "11011001": 19, "01001010": 72, "00011011": 46, "01111000": 15, "01110011": 4, "10101010": 8, "01111010": 7, "00001100": 18, "00100100": 66, "01000000": 43, "11011000": 24, "11111111": 1, "11111011": 4, "01101001": 15, "10101001": 2, "01000010": 34, "10011011": 30, "11110000": 10, "11100011": 30, "10010001": 11, "10000001": 6, "01100010": 218, "01010111": 2, "10100001": 15, "00010111": 37, "10011111": 43, "01001101": 26, "01110001": 15, "00110111": 54, "11011011": 8, "10100110": 36, "10001111": 6, "10000010": 11, "10100101": 7, "01111100": 11, "11001110": 74, "10011001": 240, "11100101": 79, "10110000": 22, "10001000": 15, "00111111": 20, "11010100": 4, "10111111": 7, "00001000": 23, "01101011": 7, "11011010": 7, "10011101": 10, "00011001": 44, "00100001": 22, "00101000": 33, "10010000": 2, "00101100": 37, "01101101": 16, "00100000": 7, "00000111": 7, "01101111": 11, "10001100": 16, "00100111": 10, "10111001": 15, "11101011": 5, "11110110": 24, "01100011": 18, "01101000": 53, "01100100": 21, "11110010": 30, "00111101": 16, "01110000": 12, "01111111": 4, "01011100": 22, "00011000": 6, "10111011": 12, "00011010": 18, "10011100": 7, "10111101": 28, "00001001": 5, "11101111": 3, "01010011": 6, "01010100": 16, "00110010": 4, "10101011": 7, "01111101": 6, "01010010": 1, "01011110": 22, "00101010": 14, "11001101": 16, "01001000": 34, "10111110": 1, "11011100": 19, "00010000": 4, "01000001": 5, "10001001": 8, "00000000": 16, "10111100": 2, "01101110": 6, "11010010": 4, "10001101": 9, "10100100": 43, "00110011": 10, "00100010": 2, "01010110": 2, "11111001": 7, "10110111": 111, "01100001": 11, "10001010": 23, "10111010": 12, "00010001": 8, "10010100": 2, "11011101": 20, "11110011": 21, "01001100": 9, "01011000": 48, "10100111": 31, "01100000": 17, "10101000": 11, "10011110": 4, "11000111": 9, "00010101": 33, "00000011": 9, "10101110": 7, "01001001": 39, "00111000": 6, "10000110": 9, "11100001": 14}, {"01010101": 1, "10110000": 1, "00011100": 1, "11110100": 2, "00000101": 2, "11100101": 3, "11001011": 6, "10101101": 1, "10000100": 2, "10000010": 1, "00111110": 2, "11010010": 1, "11101001": 1, "01000101": 2, "11100110": 6, "00111001": 10, "00010100": 4, "10111100": 1, "10100000": 2, "01110011": 6, "10101010": 6, "10011100": 2, "00101111": 2, "11010011": 1, "10000011": 3, "00111100": 15, "00010110": 3, "00101011": 1, "11111000": 1, "00101110": 2, "01111100": 7, "00000100": 2, "11111101": 4, "00100110": 4, "01110111": 4, "10101111": 4, "11011110": 21, "01100110": 2, "01110010": 2, "10101001": 4, "01101001": 6, "11100011": 4, "01001111": 15, "00100101": 8, "00001010": 30, "11100111": 7, "00011111": 406, "10100101": 5, "11100010": 13, "01110100": 7, "00010111": 18, "10011111": 274, "01100010": 35, "00110100": 9, "01000010": 27, "01100111": 6, "01111001": 21, "11110111": 10, "00100011": 5, "01010111": 5, "01010000": 1, "10101110": 10, "00100010": 6, "11111001": 8, "00000001": 9, "00011101": 18, "10010010": 3, "10000110": 11, "11100000": 12, "00011000": 25, "10111011": 26, "11111110": 18, "11000001": 2, "10001110": 57, "10110101": 13, "10001011": 9, "00110101": 3, "11111010": 1, "11101010": 36, "01001110": 19, "10111101": 13, "01011001": 88, "00111101": 23, "00010011": 28, "00101010": 14, "11001101": 11, "01101011": 11, "11011010": 3, "10110001": 51, "01011011": 2, "00011110": 9, "01001000": 180, "11001111": 44, "11001100": 195, "10111000": 9, "11110011": 3, "01001100": 112, "01101101": 7, "00100000": 5, "10011101": 30, "10010101": 19, "11001010": 69, "10011000": 17, "00011001": 171, "00100001": 12, "00001011": 5, "01001010": 264, "00011011": 38, "11011001": 62, "10010001": 38, "10000001": 5, "11001000": 115, "10011001": 331, "11001110": 223, "11010110": 12, "00001110": 23, "11000011": 5, "01000100": 2, "11000110": 19, "11011111": 16, "10010000": 2, "00101100": 20, "10100010": 19, "11000100": 70, "01011111": 52, "10101100": 1, "10000101": 6, "01000111": 4, "00010001": 14, "11101100": 39, "10010111": 45, "00110000": 26, "01101000": 6, "01100011": 1, "00110001": 20, "11000010": 8, "00000010": 5, "00111011": 17, "00001001": 30, "11101111": 14, "01010100": 2, "10110110": 5, "01111000": 4, "00101001": 21, "11010111": 4, "10110010": 9, "01011110": 20, "01010010": 7, "11111011": 7, "11111111": 3, "01011010": 14, "11010101": 7, "01110101": 3, "00011010": 2, "00111000": 32, "01001001": 19, "00101101": 10, "01000011": 3, "01000001": 1, "10111110": 4, "11011100": 14, "00010000": 17, "01010001": 2, "10111010": 8, "10001010": 12, "00111010": 4, "01001011": 7, "11011101": 9, "10010011": 25, "01101110": 14, "00000000": 2, "10001001": 11, "10110100": 2, "01101010": 55, "01110000": 9, "00001100": 27, "01111010": 10, "00100100": 20, "00000111": 4, "10001100": 14, "01101111": 4, "10100100": 26, "00110011": 2, "11110010": 5, "00110111": 37, "10001101": 5, "00110010": 4, "10101011": 5, "01011000": 15, "01100000": 18, "10100111": 5, "00001000": 33, "10111111": 6, "11010100": 7, "11100100": 27, "01000110": 9, "01110001": 15, "01001101": 21, "11000000": 5, "11000101": 1, "10011010": 14, "00001101": 5, "00101000": 11, "01011100": 19, "01111111": 4, "01111101": 5, "00001111": 10, "00111111": 9, "10001000": 13, "11101110": 5, "10011011": 7, "01000000": 18, "10100011": 10, "01101100": 12, "01100101": 6, "10110111": 34, "01100001": 7, "01111110": 6, "11010000": 4, "01111011": 6, "01110110": 4, "00010101": 9, "11000111": 11, "10111001": 4, "11101011": 4, "11110110": 4, "10010100": 3, "10100110": 15, "11011011": 22}, {"10000001": 1, "11001101": 2, "10010100": 1, "01110111": 3, "00001011": 1, "00011001": 1, "10001101": 6, "10101111": 7, "10100101": 3, "01000101": 8, "11101000": 11, "10101101": 4, "10111100": 1, "01111100": 5, "10000010": 2, "11011000": 3, "11101010": 3, "01110100": 6, "11111101": 11, "11110111": 6, "10101011": 4, "00110010": 5, "01101111": 1, "10001100": 5, "00000111": 1, "11010011": 1, "01001011": 7, "00111010": 6, "11110000": 3, "00000101": 8, "00111001": 15, "00100111": 2, "01111110": 1, "10010010": 3, "00001101": 6, "00101011": 11, "11111000": 10, "11011101": 4, "01101011": 12, "01100110": 5, "10000000": 1, "00100011": 3, "00010110": 1, "11110101": 4, "00010100": 7, "11010110": 5, "01000011": 8, "10011010": 7, "01111101": 5, "01110011": 12, "10101010": 18, "11011011": 4, "10100110": 15, "10001111": 8, "00110111": 35, "10000111": 1, "11010001": 18, "11110001": 17, "00001111": 20, "01011111": 50, "00010011": 41, "11110100": 16, "11100010": 54, "11010000": 2, "11000001": 2, "11111110": 15, "11101001": 13, "10010001": 87, "01100010": 93, "00110100": 41, "10011111": 94, "01010111": 6, "10100001": 32, "01110001": 11, "00010111": 44, "01000100": 18, "11000110": 12, "01100100": 84, "00010010": 5, "01000010": 79, "11110010": 22, "10110001": 43, "11011110": 62, "11000010": 14, "01110010": 17, "00110001": 16, "10111101": 10, "01011001": 18, "00111101": 15, "10111011": 11, "00011000": 22, "10011011": 9, "01001000": 21, "11101101": 28, "01110000": 14, "10110110": 15, "10101001": 1, "01101001": 19, "00011110": 19, "01011011": 8, "01010001": 17, "11001111": 58, "11100110": 10, "00011100": 8, "11001100": 43, "10110100": 5, "01101010": 33, "00100001": 23, "01001100": 33, "10000011": 6, "10100100": 5, "00110011": 103, "11100101": 18, "11001110": 76, "10011001": 179, "11100111": 11, "00011111": 58, "00001010": 11, "10110000": 27, "00000000": 2, "10001001": 2, "11010010": 3, "11011010": 8, "10010101": 29, "10011101": 17, "10010011": 37, "01101110": 10, "11101100": 42, "11000111": 9, "00000011": 7, "00010101": 17, "01110110": 5, "11001011": 18, "11100000": 30, "01111011": 17, "10000100": 9, "10011000": 1, "11001010": 163, "00100101": 31, "11000011": 6, "00001110": 10, "01001111": 12, "11000100": 31, "11111100": 24, "11101110": 33, "00101001": 26, "01111000": 14, "10001110": 66, "00000100": 5, "10110101": 8, "00010001": 5, "10011100": 10, "01010010": 7, "01011110": 12, "10000101": 1, "01000111": 1, "10101100": 9, "01011101": 21, "00011101": 115, "10110011": 102, "11100100": 200, "00001000": 1, "10111111": 34, "11010100": 14, "00111011": 3, "00000010": 11, "01000000": 63, "10100011": 1, "01101100": 68, "10101110": 28, "10100010": 18, "11001001": 9, "10010111": 27, "00011010": 2, "01110101": 20, "00101010": 9, "01000110": 14, "11000000": 11, "11000101": 18, "00110000": 20, "01101000": 54, "01100011": 16, "10111001": 33, "11100011": 26, "00101000": 9, "10110010": 4, "11010111": 3, "01001110": 37, "10110111": 70, "01100001": 22, "10001010": 27, "10111010": 5, "01001001": 2, "00111000": 24, "11001000": 35, "01011010": 6, "11111111": 7, "11111011": 5, "01010011": 4, "11101111": 15, "01010100": 14, "00001001": 10, "01011000": 3, "10100111": 12, "01100000": 13, "01101101": 5, "00100000": 17, "00101101": 25, "01010101": 5, "01010000": 10, "01010110": 1, "00100010": 6, "11111001": 24, "00000001": 14, "11101011": 2, "11110110": 10, "10011110": 14, "00111100": 26, "10100000": 1, "01111001": 23, "01100111": 5, "00111111": 54, "10001000": 8, "11100001": 5, "10000110": 8, "00100100": 29, "01111010": 14, "00001100": 7, "01001010": 161, "11011001": 2, "00011011": 53, "00110101": 83, "11111010": 8, "11011111": 21, "10001011": 11, "01011100": 3, "01111111": 10, "00100110": 3, "11011100": 1, "00010000": 15, "01000001": 6, "10111110": 4, "01100101": 13}, {"11110101": 1, "00011010": 1, "01110101": 1, "10000011": 2, "11110111": 2, "00110110": 1, "10101101": 2, "10010100": 1, "10101111": 1, "10010010": 2, "10110011": 5, "10111000": 3, "10001111": 2, "01100111": 5, "11100011": 2, "11100000": 3, "11110000": 2, "01110100": 5, "01010101": 1, "01110010": 3, "00110100": 3, "10000110": 4, "11100001": 1, "00000110": 2, "01101011": 4, "01100110": 2, "01111101": 6, "10010001": 11, "10100000": 3, "00100101": 8, "00111101": 11, "01100100": 6, "11111100": 2, "11011010": 13, "00111110": 4, "00010100": 2, "10011110": 4, "00001011": 3, "10000100": 2, "01100010": 14, "10110101": 1, "10101010": 11, "01110011": 4, "11101011": 5, "11110110": 13, "00110001": 2, "11001011": 13, "00110111": 25, "10000010": 7, "11100010": 24, "11100100": 1, "01111001": 59, "00010011": 10, "01011010": 10, "11111011": 15, "11111111": 13, "01000000": 15, "00011101": 17, "11011101": 35, "01011011": 1, "00011110": 37, "11011110": 114, "10110001": 8, "10011111": 167, "00010111": 18, "00000101": 5, "10101110": 51, "11100110": 1, "11001111": 94, "10000001": 6, "10010101": 3, "10011101": 82, "00011000": 69, "10111011": 16, "01000101": 4, "00101000": 24, "11101110": 38, "00001010": 50, "01011111": 55, "10111100": 3, "00101111": 7, "00110000": 27, "11001001": 7, "10100010": 10, "01001111": 36, "11010001": 9, "01010110": 1, "00100010": 4, "11111001": 25, "00000001": 16, "01111100": 22, "11001100": 44, "00011100": 12, "11000000": 8, "11001101": 1, "00101010": 5, "01011100": 41, "01111111": 27, "01111000": 14, "00101001": 37, "10011011": 29, "01001000": 199, "11100101": 2, "11010100": 1, "00001000": 50, "10111111": 64, "01010001": 23, "00111111": 63, "10001000": 27, "11000001": 3, "11111110": 36, "00101110": 14, "10011001": 131, "11001110": 127, "00001110": 19, "11000011": 8, "11010110": 6, "10001110": 156, "00000100": 11, "10110000": 4, "00011011": 6, "01001010": 25, "11011001": 74, "11011111": 25, "00101011": 5, "01110000": 8, "11101101": 1, "00001001": 65, "11101111": 40, "01010100": 6, "11001010": 64, "10011000": 67, "00111001": 17, "00011001": 135, "00100001": 47, "01110001": 14, "01001101": 43, "11001000": 63, "01011001": 113, "10111101": 15, "01001110": 14, "00111010": 4, "01001011": 21, "00000000": 3, "10001001": 64, "11010010": 5, "10010011": 19, "01101110": 4, "01111110": 22, "00011111": 156, "11100111": 16, "11010011": 5, "01111010": 11, "00100100": 31, "00001100": 40, "01110111": 8, "10010000": 4, "00101100": 30, "11010111": 4, "10110010": 11, "01100011": 5, "01101000": 56, "11101010": 38, "00001101": 12, "01000111": 8, "10101100": 5, "01011101": 8, "11000010": 13, "10011010": 29, "10100011": 15, "01101100": 36, "10100100": 5, "10111001": 40, "00100111": 3, "11111101": 12, "10110100": 1, "01101010": 18, "10101000": 2, "01100000": 24, "01011000": 27, "00010001": 4, "10010111": 13, "01010000": 6, "10100001": 5, "01010111": 13, "00100011": 8, "01000100": 19, "11000110": 14, "10001011": 22, "11111010": 6, "10001010": 30, "10111010": 12, "10110111": 18, "01100001": 8, "11101000": 27, "10011100": 23, "00100110": 8, "01100101": 6, "10100110": 18, "11011011": 26, "11011000": 8, "00111000": 46, "01001001": 22, "00101101": 11, "00111100": 10, "01000010": 7, "00000111": 3, "01101111": 20, "10001100": 8, "01001100": 89, "11110011": 13, "00001111": 30, "11110001": 2, "01111011": 3, "11101100": 9, "11000111": 9, "00010101": 9, "01110110": 9, "01010010": 2, "01011110": 24, "01000011": 4, "01101101": 21, "00100000": 14, "11110010": 3, "01101001": 12, "10101001": 6, "10111110": 1, "11011100": 1, "00010000": 12, "01000001": 5, "00110010": 6, "10101011": 11, "00111011": 2, "00000010": 1, "10001101": 17}, {"10000010": 1, "00111110": 1, "10000100": 1, "10110000": 1, "11101000": 1, "10000001": 1, "11111101": 1, "00101111": 1, "01101011": 5, "11010000": 1, "10101101": 2, "11111100": 2, "01000101": 2, "00111100": 1, "11101101": 4, "11010011": 2, "00000101": 3, "10110101": 4, "11010010": 5, "00101110": 4, "10011011": 4, "11011101": 3, "00110100": 2, "10100010": 6, "11001001": 2, "00010100": 7, "11101110": 1, "10000011": 2, "11110110": 5, "10011110": 5, "11111000": 1, "00000100": 5, "01101111": 2, "00000111": 2, "10001100": 5, "00100011": 4, "10111000": 7, "10110110": 2, "01111001": 9, "01111110": 4, "11100001": 2, "10000110": 6, "10111010": 4, "10001010": 27, "01111100": 3, "01110111": 2, "10010010": 3, "01000110": 7, "10001011": 25, "01011111": 58, "01011101": 1, "10000101": 1, "10101100": 1, "01000111": 2, "00001001": 36, "11110010": 9, "01101100": 9, "10100011": 6, "01001111": 19, "11000011": 2, "00001110": 11, "00100101": 5, "01000100": 2, "11000110": 7, "00010010": 2, "11001111": 40, "11100110": 17, "01010101": 4, "11011010": 11, "00001010": 49, "00101001": 10, "01111000": 4, "11100100": 28, "01011011": 1, "00011110": 13, "10110001": 73, "11011110": 49, "11000010": 36, "01110010": 2, "00110000": 15, "00110001": 47, "10111111": 8, "00001000": 39, "10010111": 49, "01011001": 53, "10111101": 4, "00110101": 37, "11110100": 39, "00010011": 19, "00000110": 2, "01001110": 8, "11101010": 28, "01100011": 1, "01101000": 3, "00011011": 58, "01001010": 243, "11011001": 51, "01011110": 26, "01010010": 22, "11010111": 8, "10110010": 4, "00011101": 43, "10110111": 26, "01100001": 14, "01001000": 203, "11010110": 9, "11101001": 1, "00010001": 24, "00110111": 39, "10001111": 6, "11011011": 16, "10100110": 3, "10001110": 89, "11111110": 9, "11000001": 1, "11001110": 203, "10011001": 342, "10011101": 21, "10010101": 14, "00111111": 3, "10001000": 15, "11100101": 37, "01100111": 1, "11110111": 9, "01010100": 5, "11101111": 5, "01010011": 7, "00000000": 4, "10001001": 37, "11110101": 19, "00010110": 4, "01111011": 4, "10011010": 9, "11001101": 15, "11001100": 165, "00011100": 6, "01100101": 10, "01100010": 31, "10011111": 230, "00010111": 16, "01001101": 34, "01110001": 4, "01001001": 26, "00111000": 14, "11100011": 11, "01000011": 18, "11001010": 52, "10011000": 29, "00011001": 145, "00100001": 13, "01000000": 13, "01110011": 1, "10101010": 4, "00001100": 34, "01111010": 3, "00100100": 20, "01000010": 39, "11001000": 112, "01101110": 5, "10010011": 22, "11110011": 4, "01001100": 107, "01110110": 1, "11000111": 8, "00010101": 15, "10111011": 17, "00011000": 38, "11100010": 5, "01110100": 13, "10010001": 57, "00000001": 22, "10101011": 3, "00110010": 6, "10110100": 4, "01101010": 19, "10101110": 23, "10001101": 11, "10101000": 2, "01011000": 26, "01100000": 24, "10100111": 3, "01010001": 11, "00101000": 12, "01110101": 13, "00011010": 3, "11111111": 1, "11111011": 2, "01011010": 22, "10011100": 15, "11010101": 2, "10111001": 16, "10010000": 3, "00101100": 17, "01010111": 11, "11001011": 7, "11101100": 36, "00111101": 8, "11011111": 8, "01001011": 9, "00110011": 14, "10100100": 18, "00100010": 7, "11111001": 2, "01010110": 1, "11000100": 22, "00001101": 7, "00001011": 3, "00111011": 15, "00000010": 3, "10010100": 1, "10111110": 1, "11011100": 24, "00010000": 15, "01000001": 3, "01101101": 6, "00100000": 7, "01011100": 33, "01111111": 2, "00100110": 3, "10000111": 3, "11010001": 9, "11110001": 1, "00001111": 9, "01110000": 13, "11100000": 16, "01101001": 3, "10101001": 3, "11011000": 3, "00011111": 379, "11100111": 2, "10100101": 2}, {"00000110": 1, "10110101": 3, "01111011": 2, "00101111": 1, "00010100": 1, "01010101": 2, "00101110": 2, "10111101": 4, "00010010": 2, "11011010": 3, "10110010": 2, "00100011": 2, "11010000": 2, "11000000": 2, "11000101": 3, "00000100": 3, "11110000": 1, "11101001": 1, "00110110": 6, "10011100": 7, "11101110": 5, "00101011": 3, "01110000": 3, "10011010": 4, "10100000": 6, "11111101": 4, "01111110": 1, "10011110": 7, "00001101": 6, "01111000": 6, "01101011": 14, "11110111": 22, "01111100": 4, "01100111": 6, "00101001": 4, "10111100": 2, "11010101": 6, "10101110": 3, "10000100": 10, "01101100": 26, "00101101": 10, "00111100": 12, "00010001": 10, "11001111": 8, "10010100": 2, "00011100": 6, "11001100": 111, "10111000": 6, "00111110": 2, "00100010": 3, "11111001": 10, "00000001": 8, "11101010": 5, "11000100": 75, "00100101": 24, "01001111": 18, "00011001": 60, "00100001": 27, "11100011": 6, "00000000": 1, "10001001": 33, "11010010": 9, "11000010": 9, "01110010": 22, "10110001": 133, "11011110": 19, "01011011": 1, "00011110": 25, "10010111": 69, "11110101": 28, "10000010": 9, "10100101": 17, "11101100": 77, "10101111": 23, "00001001": 26, "00001010": 28, "00111101": 34, "11110100": 22, "00010011": 48, "11101011": 13, "11110110": 31, "01100001": 5, "10110111": 35, "01111111": 1, "01011100": 14, "00011000": 25, "10111011": 30, "00000011": 2, "11000111": 9, "01110110": 3, "00010101": 12, "11010110": 12, "00001110": 4, "11000011": 12, "11110001": 3, "00001111": 20, "10000111": 7, "11010001": 19, "01011111": 20, "00010111": 58, "10011111": 120, "01100010": 119, "00110100": 23, "01100110": 4, "01000010": 24, "11011001": 19, "01001010": 233, "00011011": 33, "11100001": 2, "10000110": 15, "11010011": 7, "01110111": 6, "01000000": 42, "10101010": 17, "00111111": 8, "10001000": 5, "01010001": 15, "01000001": 2, "10111110": 25, "11011100": 22, "00010000": 8, "11100101": 19, "11001110": 187, "10011001": 247, "10011101": 8, "10010101": 10, "10110011": 16, "00111001": 12, "11001010": 67, "10011000": 30, "00011101": 44, "11101101": 7, "01011101": 2, "01000111": 2, "10101100": 15, "01001000": 128, "10011011": 10, "00101010": 6, "11001101": 17, "11110011": 2, "01001100": 99, "11001000": 137, "11111010": 17, "00110101": 67, "01000100": 3, "11000110": 28, "00001100": 34, "00100100": 21, "01111010": 9, "01100100": 4, "10001110": 56, "00110111": 39, "11011011": 7, "10100110": 21, "10001111": 8, "01110101": 41, "00101000": 7, "00110001": 39, "11000001": 1, "11111110": 10, "10010001": 58, "00011111": 234, "11100111": 18, "01100101": 10, "10110000": 13, "00111010": 1, "01001011": 7, "11100010": 32, "10010110": 8, "01110100": 9, "11100100": 40, "00001000": 27, "10111111": 31, "11010100": 5, "10010011": 23, "01101110": 3, "01101001": 6, "10101001": 6, "11111111": 8, "01011010": 5, "11111011": 5, "01011001": 24, "00101100": 3, "01101000": 8, "01100011": 26, "00110000": 28, "01001110": 25, "01000101": 14, "01001001": 12, "00111000": 4, "10110110": 6, "00110011": 38, "10100100": 12, "10000011": 9, "11100110": 30, "01010000": 9, "10100001": 8, "01010111": 8, "10111010": 5, "10001010": 10, "11100000": 12, "01110001": 18, "01001101": 17, "01000110": 6, "11111100": 14, "10100111": 7, "01011000": 21, "10010010": 7, "11101000": 4, "00100111": 8, "10111001": 22, "10001101": 5, "01000011": 22, "00111011": 42, "00000010": 5, "10101101": 8, "01111101": 11, "01111001": 10, "11101111": 2, "01010100": 10, "01010011": 4, "01101101": 6, "00100000": 2, "10110100": 14, "01101010": 20, "10001100": 6, "01101111": 1, "00110010": 5, "10101011": 9, "00100110": 2, "01011110": 14, "01010010": 20, "11110010": 9, "10001011": 9, "11011111": 11}, {"00101110": 1, "00111110": 1, "10000000": 1, "11010011": 1, "00101010": 1, "01111110": 3, "01001111": 1, "01111001": 2, "11111000": 4, "00101011": 3, "10000100": 3, "10111001": 3, "10011110": 1, "11101010": 4, "10001111": 1, "10101101": 8, "00101001": 3, "10110101": 3, "11001011": 7, "01011111": 1, "00000101": 7, "01110111": 5, "01010001": 6, "11010000": 6, "11010101": 4, "00001101": 1, "10010011": 5, "11010010": 3, "00011100": 3, "01000110": 4, "01101110": 5, "00110110": 7, "00000100": 2, "01101001": 2, "10101001": 5, "00100110": 3, "00010110": 3, "11110101": 11, "11100101": 3, "10111101": 6, "11011101": 14, "01010101": 4, "00101101": 17, "00111000": 8, "01001001": 11, "11100100": 103, "01100010": 146, "00010111": 73, "10011111": 56, "00110100": 58, "01100110": 8, "11101001": 5, "11010110": 20, "00001110": 8, "11000011": 5, "01101000": 4, "01100011": 54, "00110000": 45, "00101111": 2, "01111000": 3, "00110111": 10, "00000010": 3, "00111011": 14, "00001111": 5, "11110001": 19, "10010100": 6, "00111100": 37, "11001100": 80, "10111000": 2, "00010100": 15, "10000110": 24, "10101110": 26, "11100000": 24, "10011100": 8, "11110111": 24, "01100111": 2, "00111101": 8, "10101011": 7, "11111010": 6, "00110101": 90, "11101100": 38, "10101111": 3, "10010010": 8, "11111100": 7, "01101101": 2, "00100000": 16, "11001110": 113, "10011001": 215, "10011101": 1, "10010101": 14, "10011011": 26, "01001000": 149, "11101110": 7, "00001010": 35, "00001001": 15, "11000100": 104, "11101000": 3, "00100101": 40, "01110010": 57, "11000010": 6, "01100100": 24, "00010011": 37, "01010100": 7, "11101111": 28, "11110100": 6, "10001001": 26, "11011010": 7, "01101011": 1, "10001000": 1, "00111111": 31, "10110010": 4, "11010111": 8, "01110110": 1, "00010101": 4, "00000011": 1, "11000111": 25, "11100011": 26, "10001101": 9, "11100010": 94, "10010110": 4, "01110100": 16, "01011011": 1, "00011110": 10, "10110001": 107, "11011110": 13, "11001010": 61, "10011000": 42, "10110011": 101, "00111001": 19, "00011001": 85, "00100001": 42, "11001000": 80, "10100000": 10, "01001100": 82, "00100010": 12, "11111001": 5, "01010110": 8, "10011010": 10, "11001101": 11, "00011000": 15, "10111011": 5, "01100001": 12, "10110111": 44, "01000111": 2, "10101100": 2, "10000101": 3, "01011101": 17, "11101011": 5, "11110110": 14, "10100010": 2, "11001001": 1, "00011101": 57, "01110101": 44, "01011001": 20, "10010111": 81, "01001010": 207, "00011011": 15, "11011001": 27, "01110001": 20, "01001101": 16, "11000000": 14, "11000101": 11, "11110010": 23, "10001110": 37, "10101000": 1, "01011000": 12, "01100000": 17, "10100111": 33, "00000001": 11, "01011100": 13, "01111111": 16, "01000010": 15, "11111011": 1, "01011010": 14, "11111111": 23, "01000000": 24, "00110011": 60, "10100100": 5, "10000011": 10, "10100101": 7, "10000010": 9, "10100110": 8, "11011011": 12, "11000001": 4, "11111110": 9, "10110110": 40, "10010000": 1, "00101100": 3, "10110000": 21, "01001110": 21, "11100110": 23, "11001111": 8, "00100111": 5, "11000110": 26, "01000100": 19, "10010001": 24, "10111010": 5, "10001010": 29, "00110001": 42, "01111100": 9, "01010010": 3, "01011110": 6, "11010100": 5, "00001000": 20, "10111111": 29, "10100001": 26, "01010111": 17, "01111101": 25, "11011000": 4, "01001011": 8, "01101111": 3, "00000111": 2, "10001100": 3, "10110100": 18, "01101010": 13, "01110000": 12, "11101101": 7, "10001011": 8, "01000101": 12, "10111100": 6, "00011111": 219, "11100111": 16, "01111010": 3, "00001100": 29, "00100100": 20, "01110011": 12, "10101010": 17, "01100101": 3, "10100011": 2, "01101100": 18, "10000111": 6, "11010001": 6, "00101000": 1, "11111101": 7, "10111110": 1, "11011100": 6, "00010000": 11, "01000001": 1, "01000011": 6}, {"11011000": 1, "10000000": 2, "01010101": 2, "00000110": 1, "00010100": 1, "11010000": 2, "00000101": 1, "11011010": 2, "10010100": 7, "00101000": 5, "00010001": 2, "10001101": 3, "00001010": 3, "00001101": 5, "00011001": 4, "10000001": 7, "11100110": 6, "10111001": 1, "11001000": 11, "00111001": 1, "00011100": 2, "00100110": 5, "00101111": 2, "10101111": 2, "11000001": 1, "11111110": 20, "00010011": 5, "01111101": 6, "10000011": 5, "10011011": 4, "11111000": 1, "00101011": 5, "01111111": 10, "01011100": 9, "01111110": 7, "00101101": 9, "11010101": 4, "10010001": 11, "11111111": 3, "11111011": 25, "00010110": 2, "11110101": 9, "11111101": 11, "01000101": 11, "10100000": 10, "01010111": 14, "11101001": 2, "10101110": 27, "10111101": 12, "01011001": 33, "10000010": 9, "10011010": 10, "01001110": 2, "11100100": 66, "00110000": 129, "01100110": 51, "10011111": 17, "00110100": 57, "01100010": 59, "00010111": 117, "11100011": 36, "11110000": 15, "01000011": 14, "10111011": 41, "00011000": 11, "00110111": 24, "10011101": 11, "10010101": 9, "11000011": 7, "00001110": 4, "00100101": 65, "10011000": 6, "11001010": 13, "01001111": 9, "01101010": 27, "11001111": 22, "00101001": 44, "01111000": 7, "01101100": 1, "10100011": 114, "01100011": 33, "01101000": 11, "11101010": 24, "01110111": 32, "11010011": 6, "01111001": 34, "01100111": 14, "01000110": 8, "11000000": 21, "11000101": 8, "01110001": 74, "01001101": 10, "01010000": 2, "00100011": 32, "11111100": 22, "11000100": 39, "11011101": 12, "10110011": 90, "00110011": 2, "10100100": 42, "11110010": 42, "11111010": 17, "00110101": 156, "10100010": 65, "10010011": 36, "01101110": 20, "10100110": 76, "11011011": 13, "00100001": 121, "00101010": 8, "11001101": 8, "10110001": 76, "11011110": 30, "01011011": 5, "00011110": 11, "01100001": 3, "10110111": 55, "11101011": 11, "11110110": 71, "01111100": 26, "01000010": 10, "10110101": 84, "10001110": 16, "00000100": 12, "01011101": 4, "01000111": 5, "10000101": 6, "10101100": 12, "11101101": 20, "01110000": 2, "11101111": 19, "01010011": 1, "01010100": 20, "00001001": 21, "00100111": 47, "00100100": 70, "00001100": 17, "01111010": 19, "01100100": 63, "01000100": 1, "11000110": 34, "10001011": 22, "11010111": 4, "10110010": 126, "01011110": 10, "01010010": 13, "00111110": 3, "10111000": 7, "11001100": 8, "01100101": 34, "01110010": 27, "11000010": 35, "11100101": 49, "00001000": 12, "11010100": 10, "10111111": 54, "01010001": 29, "01001100": 16, "11110011": 43, "00110001": 24, "01010110": 2, "00100010": 14, "11111001": 14, "00000001": 28, "01110100": 41, "11100010": 30, "01110101": 35, "00111011": 4, "00000010": 6, "10101101": 5, "11110100": 47, "11010110": 16, "10011001": 37, "11001110": 20, "11010010": 6, "00000000": 7, "10001001": 7, "00000011": 2, "00010101": 7, "11000111": 16, "01110110": 15, "11101100": 13, "11001011": 4, "10111100": 4, "01011111": 15, "01001000": 7, "00111010": 14, "00101110": 6, "10110110": 15, "01111011": 16, "10000100": 3, "10000111": 1, "11010001": 10, "11110001": 9, "00001111": 8, "01000000": 14, "00111111": 43, "11100000": 14, "10101000": 1, "01011000": 6, "01100000": 81, "10100111": 17, "00011011": 9, "01001010": 31, "11011001": 15, "00001011": 1, "10010111": 50, "01101011": 15, "10101010": 23, "01110011": 24, "00111000": 37, "01001001": 8, "00110110": 41, "11101000": 20, "11011100": 7, "10111110": 7, "00010000": 20, "01000001": 2, "00111101": 6, "00011111": 3, "11100111": 63, "11011111": 9, "10000110": 15, "11100001": 18, "11101110": 7, "10010000": 14, "00101100": 21, "00011101": 22, "10101001": 8, "01101001": 7, "01101111": 6, "10001100": 10, "10111010": 19, "10001010": 6, "00111100": 6, "01101101": 15, "00100000": 14, "10101011": 13, "00110010": 37, "10011100": 5}, {"10000001": 1, "01100111": 1, "10111101": 1, "00111110": 1, "11111110": 2, "01100110": 2, "11010000": 1, "10011110": 4, "11001011": 2, "00101010": 2, "11101000": 2, "01110000": 5, "00000101": 1, "01111001": 3, "00101110": 1, "10101110": 5, "01000101": 4, "01111100": 7, "00111100": 1, "00110110": 2, "10001111": 3, "00101001": 4, "10111000": 6, "10001101": 4, "10010010": 5, "11000000": 4, "11000101": 5, "10101010": 4, "11110000": 2, "00010010": 2, "00000001": 11, "10100001": 1, "01010111": 8, "01111101": 2, "01101011": 9, "01111110": 3, "11101110": 6, "00101011": 2, "00101000": 10, "10110011": 2, "00000100": 10, "01101101": 6, "00100000": 2, "01010011": 2, "01010100": 6, "10111010": 4, "10001010": 9, "00101100": 9, "10010000": 2, "11011010": 2, "10100101": 11, "10000010": 6, "11100001": 2, "10000110": 13, "11010011": 5, "11001111": 24, "11100110": 26, "10011101": 12, "10010101": 16, "11101100": 54, "10101111": 11, "01000110": 6, "11100010": 23, "00010111": 59, "01100010": 83, "10011111": 150, "00110100": 11, "01001101": 17, "01110001": 10, "01000111": 2, "10101100": 9, "11101101": 4, "01110100": 12, "10010110": 4, "01100001": 12, "10110111": 55, "00000000": 1, "10001001": 30, "11010010": 8, "11011111": 14, "11001001": 3, "10100010": 12, "01111011": 2, "10000100": 3, "00100101": 9, "11000011": 6, "00001110": 10, "01001111": 18, "11001010": 74, "10011000": 20, "00111001": 5, "00011001": 84, "00100001": 24, "11000010": 19, "01110010": 8, "10110001": 122, "11011110": 15, "00011100": 8, "11001100": 148, "00111101": 20, "01111000": 8, "10010001": 65, "00010011": 39, "11110100": 34, "00110001": 44, "00110000": 25, "00101111": 3, "00001111": 9, "11001000": 121, "11001101": 19, "10110010": 8, "11010111": 1, "00001001": 28, "00001101": 10, "11110011": 10, "01001100": 118, "01001000": 166, "10011011": 24, "11011101": 2, "00011101": 43, "00001010": 28, "01000100": 1, "11000110": 24, "10011001": 224, "11001110": 197, "11010110": 5, "01010000": 6, "00100011": 5, "01000000": 44, "10100011": 4, "01101100": 9, "10010111": 100, "11010001": 16, "10000111": 5, "11110101": 28, "01011001": 25, "01100101": 17, "00000010": 6, "00111011": 20, "10001110": 66, "10110101": 10, "00110111": 33, "11011011": 7, "10100110": 20, "00100110": 4, "00011000": 23, "10111011": 28, "01110110": 1, "11000111": 11, "00000011": 1, "00010101": 13, "01111111": 1, "01011100": 16, "01110101": 20, "00111111": 11, "10001000": 16, "01010001": 14, "11100101": 33, "11100100": 47, "00001000": 30, "10111111": 45, "11010100": 7, "00001100": 49, "01111010": 7, "00100100": 20, "00011111": 278, "11100111": 15, "00111010": 5, "01001011": 8, "00010001": 16, "01000010": 33, "01011000": 15, "01100000": 17, "10100111": 6, "11000100": 74, "10110110": 9, "10010011": 31, "01101110": 6, "01011111": 32, "01101010": 16, "10110100": 11, "00011110": 15, "01011011": 3, "10101001": 2, "01101001": 9, "01000011": 22, "00110010": 1, "10101011": 8, "01010101": 3, "00111000": 14, "01001001": 19, "10111001": 35, "00100111": 3, "01001110": 34, "10110000": 5, "00100010": 1, "01010110": 2, "11111001": 7, "11111101": 4, "00110101": 56, "11111010": 10, "11101011": 8, "11110110": 18, "00011011": 33, "01001010": 261, "11011001": 28, "11110010": 4, "10100000": 2, "00110011": 18, "10100100": 14, "10000011": 10, "01010010": 28, "01011110": 23, "10011100": 12, "11111011": 2, "01011010": 8, "01100011": 8, "01101000": 14, "11101010": 8, "11110111": 12, "11011000": 1, "10011010": 8, "00010000": 8, "10111110": 10, "11011100": 13, "01000001": 6, "00000111": 1, "10001100": 13, "11100000": 17, "11111100": 9, "11100011": 5, "10001011": 6}], "job_id": ["cmm5m08hu2povi6lndn0", "cmm5m0v4mi97k7ka5vbg", "cmm5m18hu2povi6lndsg", "cmm5m2jrga5j1uak2ssg", "cmm5m38hu2povi6lne1g", "cmm5m3knktricihd24vg", "cmm5m4rrga5j1uak2t60", "cmm5m5f4mi97k7ka5vtg", "cmm5m5rrga5j1uak2tb0", "cmm5m68hu2povi6lnecg", "cmm5m6tmtr96u83rb55g", "cmm5m9jrga5j1uak2tj0", "cmm5maohu2povi6lneqg", "cmm5mb8hu2povi6lnes0", "cmm5mcjrga5j1uak2tu0", "cmm5mdv4mi97k7ka60n0", "cmm5meampoeld4nnvtng", "cmm5mflmtr96u83rb61g", "cmm5mg0hu2povi6lnfb0", "cmm5mhbrga5j1uak2uc0", "cmm5mhrrga5j1uak2ueg"]}, "optimized": {"angles": [0.879762017518, 1.115055977201, -0.016556483887], "cost": 99.2572, "measurement_outcomes": {"10000010": 1, "00111110": 1, "10000100": 1, "10110000": 1, "11101000": 1, "10000001": 1, "11111101": 1, "00101111": 1, "01101011": 5, "11010000": 1, "10101101": 2, "11111100": 2, "01000101": 2, "00111100": 1, "11101101": 4, "11010011": 2, "00000101": 3, "10110101": 4, "11010010": 5, "00101110": 4, "10011011": 4, "11011101": 3, "00110100": 2, "10100010": 6, "11001001": 2, "00010100": 7, "11101110": 1, "10000011": 2, "11110110": 5, "10011110": 5, "11111000": 1, "00000100": 5, "01101111": 2, "00000111": 2, "10001100": 5, "00100011": 4, "10111000": 7, "10110110": 2, "01111001": 9, "01111110": 4, "11100001": 2, "10000110": 6, "10111010": 4, "10001010": 27, "01111100": 3, "01110111": 2, "10010010": 3, "01000110": 7, "10001011": 25, "01011111": 58, "01011101": 1, "10000101": 1, "10101100": 1, "01000111": 2, "00001001": 36, "11110010": 9, "01101100": 9, "10100011": 6, "01001111": 19, "11000011": 2, "00001110": 11, "00100101": 5, "01000100": 2, "11000110": 7, "00010010": 2, "11001111": 40, "11100110": 17, "01010101": 4, "11011010": 11, "00001010": 49, "00101001": 10, "01111000": 4, "11100100": 28, "01011011": 1, "00011110": 13, "10110001": 73, "11011110": 49, "11000010": 36, "01110010": 2, "00110000": 15, "00110001": 47, "10111111": 8, "00001000": 39, "10010111": 49, "01011001": 53, "10111101": 4, "00110101": 37, "11110100": 39, "00010011": 19, "00000110": 2, "01001110": 8, "11101010": 28, "01100011": 1, "01101000": 3, "00011011": 58, "01001010": 243, "11011001": 51, "01011110": 26, "01010010": 22, "11010111": 8, "10110010": 4, "00011101": 43, "10110111": 26, "01100001": 14, "01001000": 203, "11010110": 9, "11101001": 1, "00010001": 24, "00110111": 39, "10001111": 6, "11011011": 16, "10100110": 3, "10001110": 89, "11111110": 9, "11000001": 1, "11001110": 203, "10011001": 342, "10011101": 21, "10010101": 14, "00111111": 3, "10001000": 15, "11100101": 37, "01100111": 1, "11110111": 9, "01010100": 5, "11101111": 5, "01010011": 7, "00000000": 4, "10001001": 37, "11110101": 19, "00010110": 4, "01111011": 4, "10011010": 9, "11001101": 15, "11001100": 165, "00011100": 6, "01100101": 10, "01100010": 31, "10011111": 230, "00010111": 16, "01001101": 34, "01110001": 4, "01001001": 26, "00111000": 14, "11100011": 11, "01000011": 18, "11001010": 52, "10011000": 29, "00011001": 145, "00100001": 13, "01000000": 13, "01110011": 1, "10101010": 4, "00001100": 34, "01111010": 3, "00100100": 20, "01000010": 39, "11001000": 112, "01101110": 5, "10010011": 22, "11110011": 4, "01001100": 107, "01110110": 1, "11000111": 8, "00010101": 15, "10111011": 17, "00011000": 38, "11100010": 5, "01110100": 13, "10010001": 57, "00000001": 22, "10101011": 3, "00110010": 6, "10110100": 4, "01101010": 19, "10101110": 23, "10001101": 11, "10101000": 2, "01011000": 26, "01100000": 24, "10100111": 3, "01010001": 11, "00101000": 12, "01110101": 13, "00011010": 3, "11111111": 1, "11111011": 2, "01011010": 22, "10011100": 15, "11010101": 2, "10111001": 16, "10010000": 3, "00101100": 17, "01010111": 11, "11001011": 7, "11101100": 36, "00111101": 8, "11011111": 8, "01001011": 9, "00110011": 14, "10100100": 18, "00100010": 7, "11111001": 2, "01010110": 1, "11000100": 22, "00001101": 7, "00001011": 3, "00111011": 15, "00000010": 3, "10010100": 1, "10111110": 1, "11011100": 24, "00010000": 15, "01000001": 3, "01101101": 6, "00100000": 7, "01011100": 33, "01111111": 2, "00100110": 3, "10000111": 3, "11010001": 9, "11110001": 1, "00001111": 9, "01110000": 13, "11100000": 16, "01101001": 3, "10101001": 3, "11011000": 3, "00011111": 379, "11100111": 2, "10100101": 2}, "job_id": "cmm5meampoeld4nnvtng", "eval_number": 17}}